{
  "events": [
    
    {
      "date": "",
      "time": "22:00 UTC -5",
      "category": "GOLF",
      "info": "LPGA",
      "title": "LPGA Shanghai",
      "url": "https://voodc.com/embed/85818c919c8d9e86847a8597a5909885.html"
    },
    {
      "date": "",
      "time": "22:00 UTC -5",
      "category": "GOLF",
      "info": "PGA Tour",
      "title": "Baycurrent Classic",
      "url": "https://voodc.com/embed/85818c919c8d9e86847a8597a58d9886.html"
    },
    {
      "date": "",
      "time": "01:10 UTC -5",
      "category": "RUGBY",
      "info": "New Zealand Bunnings NPC",
      "title": "Otago - Waikato",
      "url": "https://voodc.com/embed/85818c919c8e9f8a847a8595a28d988b.html"
    },
    {
      "date": "",
      "time": "01:40 UTC -5",
      "category": "TENNIS",
      "info": "WTA",
      "title": "WTA Wuhan - Court 1 Chan/Jiang - Hunter/Siniakova",
      "url": "https://voodc.com/embed/85818c919c8ea188847a859aa488988c.html"
    },
    {
      "date": "",
      "time": "01:50 UTC -5",
      "category": "TENNIS",
      "info": "WTA",
      "title": "WTA Wuhan - Center Court Siegemund - Gauff",
      "url": "https://voodc.com/embed/85818c919c8ea284847a859aa487988d.html"
    },
    {
      "date": "",
      "time": "02:00 UTC -5",
      "category": "TENNIS",
      "info": "ATP",
      "title": "ATP Shanghai Rinderknech - Auger-Aliassime",
      "url": "https://voodc.com/embed/85818c919c8ea28a847a859aa48c988584.html"
    },
    {
      "date": "",
      "time": "03:00 UTC -5",
      "category": "TENNIS",
      "info": "WTA",
      "title": "WTA Mallorca Carle - Kostovic",
      "url": "https://voodc.com/embed/85818c919c8f9c86847a859aa48f988585.html"
    },
    {
      "date": "",
      "time": "03:00 UTC -5",
      "category": "TENNIS",
      "info": "WTA",
      "title": "WTA Wuhan - Court 1 Mihalikova/Nicholls - Noskova/Sramkova",
      "url": "https://voodc.com/embed/85818c919c8f9c86847a859aa488988586.html"
    },
    {
      "date": "",
      "time": "04:30 UTC -5",
      "category": "TENNIS",
      "info": "WTA",
      "title": "WTA Mallorca Radivojevic - Noha Akugue",
      "url": "https://voodc.com/embed/85818c919c8fa18a847a859aa48f988587.html"
    },
    {
      "date": "",
      "time": "04:30 UTC -5",
      "category": "TENNIS",
      "info": "WTA",
      "title": "WTA Wuhan - Court 1 Siegemund/Stollar - Jovic/Olmos",
      "url": "https://voodc.com/embed/85818c919c8fa18a847a859aa488988588.html"
    },
    {
      "date": "",
      "time": "05:00 UTC -5",
      "category": "SOCCER",
      "info": "J3-League",
      "title": "Osaka - Ryukyu",
      "url": "https://voodc.com/embed/85818c919c909988847a859a9c87988589.html"
    },
    {
      "date": "",
      "time": "05:20 UTC -5",
      "category": "SOCCER",
      "info": "Friendly",
      "title": "Japan - Paraguay",
      "url": "https://voodc.com/embed/85818c919c909a8a847a859a9c8898858a.html"
    },
    {
      "date": "",
      "time": "05:30 UTC -5",
      "category": "TENNIS",
      "info": "ATP",
      "title": "ATP Shanghai Medvedev - De Minaur",
      "url": "https://voodc.com/embed/85818c919c909b86847a859aa48c988785.html"
    },
    {
      "date": "",
      "time": "06:00 UTC -5",
      "category": "SOCCER",
      "info": "Friendly",
      "title": "South Korea - Brazil",
      "url": "https://voodc.com/embed/85818c919c909d84847a859a9c8998858b.html"
    },
    {
      "date": "",
      "time": "06:00 UTC -5",
      "category": "TENNIS",
      "info": "WTA",
      "title": "WTA Wuhan - Center Court Paolini - Swiatek",
      "url": "https://voodc.com/embed/85818c919c909d84847a859aa487988786.html"
    },
    {
      "date": "",
      "time": "06:30 UTC -5",
      "category": "FIELD HOCKEY",
      "info": "Euro Hockey League",
      "title": "St. Germain - Hamburger Polo Club",
      "url": "https://voodc.com/embed/85818c919c909e8c847a8599a58f98878a.html"
    },
    {
      "date": "",
      "time": "06:30 UTC -5",
      "category": "BILLIARD",
      "info": "Snooker",
      "title": "Grand Prix Snooker - Table 1",
      "url": "https://voodc.com/embed/85818c919c909e8c847a85979c879887.html"
    },
    {
      "date": "",
      "time": "06:30 UTC -5",
      "category": "BILLIARD",
      "info": "Snooker",
      "title": "Grand Prix Snooker - Table 2",
      "url": "https://voodc.com/embed/85818c919c909e8c847a85979c889888.html"
    },
    {
      "date": "",
      "time": "06:30 UTC -5",
      "category": "BILLIARD",
      "info": "Snooker",
      "title": "Grand Prix Snooker - Table 3",
      "url": "https://voodc.com/embed/85818c919c909e8c847a85979c899889.html"
    },
    {
      "date": "",
      "time": "06:30 UTC -5",
      "category": "BILLIARD",
      "info": "Snooker",
      "title": "Grand Prix Snooker - Table 4",
      "url": "https://voodc.com/embed/85818c919c909e8c847a85979c8a988a.html"
    },
    {
      "date": "",
      "time": "07:00 UTC -5",
      "category": "BASKETBALL",
      "info": "NBA",
      "title": "Brooklyn Nets vs. Phoenix Suns",
      "url": "https://voodc.com/embed/85818c919c90a08a847a859a9c8a98858c.html"
    },
    {
      "date": "",
      "time": "07:00 UTC -5",
      "category": "TENNIS",
      "info": "WTA",
      "title": "WTA Mallorca Sierra - Gorgodze",
      "url": "https://voodc.com/embed/85818c919c90a08a847a859aa48f988787.html"
    },
    {
      "date": "",
      "time": "07:00 UTC -5",
      "category": "GOLF",
      "info": "DP World Tour",
      "title": "Open de Espana",
      "url": "https://voodc.com/embed/85818c919c90a08a847a8597a58d98878c.html"
    },
    {
      "date": "",
      "time": "07:30 UTC -5",
      "category": "COMBAT SPORT",
      "info": "MMA",
      "title": "ONE Friday Fights 128: Irvine vs. Rambong",
      "url": "https://voodc.com/embed/85818c919c90a288847a8599a58e98878d.html"
    },
    {
      "date": "",
      "time": "07:30 UTC -5",
      "category": "TENNIS",
      "info": "WTA",
      "title": "WTA Wuhan - Center Court Andreescu/Yuan - Danilina/Krunic",
      "url": "https://voodc.com/embed/85818c919c90a288847a859aa487988788.html"
    },
    {
      "date": "",
      "time": "07:45 UTC -5",
      "category": "SOCCER",
      "info": "Friendly",
      "title": "Uruguay - Dominican Republic",
      "url": "https://voodc.com/embed/85818c919d879987847a859a9c8b98858d.html"
    },
    {
      "date": "",
      "time": "08:00 UTC -5",
      "category": "SOCCER",
      "info": "Croatia Prva NL",
      "title": "Rudes - Bijelo Brdo",
      "url": "https://voodc.com/embed/85818c919d879a86847a859a9c8c988684.html"
    },
    {
      "date": "",
      "time": "08:00 UTC -5",
      "category": "SOCCER",
      "info": "Friendly",
      "title": "Indonesia U23 - India U23",
      "url": "https://voodc.com/embed/85818c919d879a86847a859a9c8d988685.html"
    },
    {
      "date": "",
      "time": "08:00 UTC -5",
      "category": "SOCCER",
      "info": "World Cup Qualifier",
      "title": "Gambia - Gabon",
      "url": "https://voodc.com/embed/85818c919d879a86847a859a9c8e988686.html"
    },
    {
      "date": "",
      "time": "08:00 UTC -5",
      "category": "SOCCER",
      "info": "World Cup Qualifier",
      "title": "Seychelles - Ivory Coast",
      "url": "https://voodc.com/embed/85818c919d879a86847a859a9c8f988687.html"
    },
    {
      "date": "",
      "time": "08:00 UTC -5",
      "category": "SOCCER",
      "info": "World Cup Qualifier",
      "title": "South Sudan - Senegal",
      "url": "https://voodc.com/embed/85818c919d879a86847a859a9c90988688.html"
    },
    {
      "date": "",
      "time": "08:00 UTC -5",
      "category": "SOCCER",
      "info": "World Cup Qualifier",
      "title": "Sudan - Mauritania",
      "url": "https://voodc.com/embed/85818c919d879a86847a859a9d87988689.html"
    },
    {
      "date": "",
      "time": "08:00 UTC -5",
      "category": "SOCCER",
      "info": "World Cup Qualifier",
      "title": "Togo - D.R. Congo",
      "url": "https://voodc.com/embed/85818c919d879a86847a859a9d8898868a.html"
    },
    {
      "date": "",
      "time": "08:30 UTC -5",
      "category": "TENNIS",
      "info": "WTA",
      "title": "WTA Mallorca Lazaro Garcia - Bejlek",
      "url": "https://voodc.com/embed/85818c919d879c84847a859aa48f988789.html"
    },
    {
      "date": "",
      "time": "08:45 UTC -5",
      "category": "FIELD HOCKEY",
      "info": "Euro Hockey League",
      "title": "Montrouge - Wien",
      "url": "https://voodc.com/embed/85818c919d879c8d847a8599a59098878b.html"
    },
    {
      "date": "",
      "time": "09:00 UTC -5",
      "category": "SOCCER",
      "info": "Friendly",
      "title": "Romania U20 - Czech Republic U20",
      "url": "https://voodc.com/embed/85818c919d879d8c847a859a9d8998868d.html"
    },
    {
      "date": "",
      "time": "09:00 UTC -5",
      "category": "SOCCER",
      "info": "World Cup Qualifier",
      "title": "Kazakhstan - Liechtenstein",
      "url": "https://voodc.com/embed/85818c919d879d8c847a859a9d8a988784.html"
    },
    {
      "date": "",
      "time": "09:00 UTC -5",
      "category": "HOCKEY",
      "info": "KHL",
      "title": "Magnitogorsk - Nizhny Novgorod",
      "url": "https://voodc.com/embed/85818c919d879d8c847a859a9d8b98868b.html"
    },
    {
      "date": "",
      "time": "09:00 UTC -5",
      "category": "HOCKEY",
      "info": "KHL",
      "title": "Yekaterinburg - Avangard Omsk",
      "url": "https://voodc.com/embed/85818c919d879d8c847a859a9d8c98868c.html"
    },
    {
      "date": "",
      "time": "10:00 UTC -5",
      "category": "SOCCER",
      "info": "Euro Qualifier",
      "title": "North Macedonia U21 - Armenia U21",
      "url": "https://voodc.com/embed/85818c919d87a188847a859a9d8d98898c.html"
    },
    {
      "date": "",
      "time": "10:00 UTC -5",
      "category": "HOCKEY",
      "info": "CZ Extraliga",
      "title": "Karlovy Vary - HC Ocelari Trinec",
      "url": "https://voodc.com/embed/85818c919d87a188847a85979c8c988884.html"
    },
    {
      "date": "",
      "time": "10:00 UTC -5",
      "category": "HOCKEY",
      "info": "KHL",
      "title": "HC Lada - Novosibirsk",
      "url": "https://voodc.com/embed/85818c919d87a188847a85979c8d988885.html"
    },
    {
      "date": "",
      "time": "10:30 UTC -5",
      "category": "HOCKEY",
      "info": "CZ Extraliga",
      "title": "Ceske Budejovice - Slovan Liberec",
      "url": "https://voodc.com/embed/85818c919d889986847a85979c8e988887.html"
    },
    {
      "date": "",
      "time": "10:30 UTC -5",
      "category": "HOCKEY",
      "info": "CZ Extraliga",
      "title": "HC Litvinov - Kladno",
      "url": "https://voodc.com/embed/85818c919d889986847a85979c8f988888.html"
    },
    {
      "date": "",
      "time": "10:30 UTC -5",
      "category": "HOCKEY",
      "info": "CZ Extraliga",
      "title": "Mlada Boleslav - Mountfield HK",
      "url": "https://voodc.com/embed/85818c919d889986847a85979c90988889.html"
    },
    {
      "date": "",
      "time": "10:30 UTC -5",
      "category": "HOCKEY",
      "info": "Liiga",
      "title": "Hameenlinna - SaiPa",
      "url": "https://voodc.com/embed/85818c919d889986847a85979d8798888a.html"
    },
    {
      "date": "",
      "time": "10:30 UTC -5",
      "category": "HOCKEY",
      "info": "Liiga",
      "title": "Ilves - IFK Helsinki",
      "url": "https://voodc.com/embed/85818c919d889986847a85979d8898888b.html"
    },
    {
      "date": "",
      "time": "10:30 UTC -5",
      "category": "HOCKEY",
      "info": "Liiga",
      "title": "Jukurit - Karpat Oulu",
      "url": "https://voodc.com/embed/85818c919d889986847a85979d8998888c.html"
    },
    {
      "date": "",
      "time": "10:30 UTC -5",
      "category": "HOCKEY",
      "info": "Liiga",
      "title": "KalPa Kuopio - TPS Turku",
      "url": "https://voodc.com/embed/85818c919d889986847a85979d8a98888d.html"
    },
    {
      "date": "",
      "time": "10:30 UTC -5",
      "category": "HOCKEY",
      "info": "Liiga",
      "title": "Lukko Rauma - JYP",
      "url": "https://voodc.com/embed/85818c919d889986847a85979d8b988984.html"
    },
    {
      "date": "",
      "time": "10:30 UTC -5",
      "category": "HOCKEY",
      "info": "Mestis",
      "title": "KeuPa - Hermes",
      "url": "https://voodc.com/embed/85818c919d889986847a85979d8c988985.html"
    },
    {
      "date": "",
      "time": "10:30 UTC -5",
      "category": "HOCKEY",
      "info": "Mestis",
      "title": "Kiekko-Pojat - Jokerit",
      "url": "https://voodc.com/embed/85818c919d889986847a85979d8d988986.html"
    },
    {
      "date": "",
      "time": "10:30 UTC -5",
      "category": "HOCKEY",
      "info": "Mestis",
      "title": "RoKi - Kettera",
      "url": "https://voodc.com/embed/85818c919d889986847a85979d8e988987.html"
    },
    {
      "date": "",
      "time": "10:30 UTC -5",
      "category": "HOCKEY",
      "info": "Mestis",
      "title": "TUTO - K-Vantaa",
      "url": "https://voodc.com/embed/85818c919d889986847a85979d8f988988.html"
    },
    {
      "date": "",
      "time": "10:30 UTC -5",
      "category": "HOCKEY",
      "info": "Slovak Extraliga",
      "title": "Ban. Bystrica - Spisska Nova Ves",
      "url": "https://voodc.com/embed/85818c919d889986847a85979d90988989.html"
    },
    {
      "date": "",
      "time": "10:30 UTC -5",
      "category": "HOCKEY",
      "info": "Slovak Extraliga",
      "title": "Zilina - HC Kosice",
      "url": "https://voodc.com/embed/85818c919d889986847a85979e8798898a.html"
    },
    {
      "date": "",
      "time": "10:30 UTC -5",
      "category": "VOLLEYBALL",
      "info": "Poland",
      "title": "Budowlani Lodz W - Mielec W",
      "url": "https://voodc.com/embed/85818c919d889986847a85979e8898898b.html"
    },
    {
      "date": "",
      "time": "11:00 UTC -5",
      "category": "SOCCER",
      "info": "Euro Qualifier",
      "title": "Bosnia & Herzegovina U21 - Netherlands U21",
      "url": "https://voodc.com/embed/85818c919d889b84847a85979e89988a8d.html"
    },
    {
      "date": "",
      "time": "11:00 UTC -5",
      "category": "SOCCER",
      "info": "Euro Qualifier",
      "title": "Czech Republic U21 - Azerbaijan U21",
      "url": "https://voodc.com/embed/85818c919d889b84847a85979e8a988b84.html"
    },
    {
      "date": "",
      "time": "11:00 UTC -5",
      "category": "SOCCER",
      "info": "Euro Qualifier",
      "title": "Denmark U21 - Austria U21",
      "url": "https://voodc.com/embed/85818c919d889b84847a85979e8b988b85.html"
    },
    {
      "date": "",
      "time": "11:00 UTC -5",
      "category": "SOCCER",
      "info": "Euro Qualifier",
      "title": "Estonia U21 - Luxembourg U21",
      "url": "https://voodc.com/embed/85818c919d889b84847a85979e8c988b86.html"
    },
    {
      "date": "",
      "time": "11:00 UTC -5",
      "category": "SOCCER",
      "info": "Euro Qualifier",
      "title": "Faroe Islands U21 - France U21",
      "url": "https://voodc.com/embed/85818c919d889b84847a85979e8d988b87.html"
    },
    {
      "date": "",
      "time": "11:00 UTC -5",
      "category": "SOCCER",
      "info": "Euro Qualifier",
      "title": "Germany U21 - Greece U21",
      "url": "https://voodc.com/embed/85818c919d889b84847a85979e8e988b88.html"
    },
    {
      "date": "",
      "time": "11:00 UTC -5",
      "category": "SOCCER",
      "info": "Euro Qualifier",
      "title": "Israel U21 - Slovenia U21",
      "url": "https://voodc.com/embed/85818c919d889b84847a85979e8f988b89.html"
    },
    {
      "date": "",
      "time": "11:00 UTC -5",
      "category": "SOCCER",
      "info": "Euro Qualifier",
      "title": "Moldova U21 - England U21",
      "url": "https://voodc.com/embed/85818c919d889b84847a85979e90988b8a.html"
    },
    {
      "date": "",
      "time": "11:00 UTC -5",
      "category": "SOCCER",
      "info": "Euro Qualifier",
      "title": "Poland U21 - Montenegro U21",
      "url": "https://voodc.com/embed/85818c919d889b84847a85979f87988b8b.html"
    },
    {
      "date": "",
      "time": "11:00 UTC -5",
      "category": "SOCCER",
      "info": "Euro Qualifier",
      "title": "Ukraine U21 - Hungary U21",
      "url": "https://voodc.com/embed/85818c919d889b84847a85979f88988b8c.html"
    },
    {
      "date": "",
      "time": "11:00 UTC -5",
      "category": "SOCCER",
      "info": "Friendly",
      "title": "Bolivia - Jordan",
      "url": "https://voodc.com/embed/85818c919d889b84847a85979f89988b8d.html"
    },
    {
      "date": "",
      "time": "11:00 UTC -5",
      "category": "SOCCER",
      "info": "Friendly",
      "title": "Portugal U20 - Germany U20",
      "url": "https://voodc.com/embed/85818c919d889b84847a85979f8a988c84.html"
    },
    {
      "date": "",
      "time": "11:00 UTC -5",
      "category": "SOCCER",
      "info": "Friendly",
      "title": "Romania U21 - Serbia U21",
      "url": "https://voodc.com/embed/85818c919d889b84847a85979f8b988c85.html"
    },
    {
      "date": "",
      "time": "11:00 UTC -5",
      "category": "SOCCER",
      "info": "World Cup Qualifier",
      "title": "Lesotho - Nigeria",
      "url": "https://voodc.com/embed/85818c919d889b84847a85979f8c988c86.html"
    },
    {
      "date": "",
      "time": "11:00 UTC -5",
      "category": "SOCCER",
      "info": "World Cup Qualifier",
      "title": "Rwanda - Benin",
      "url": "https://voodc.com/embed/85818c919d889b84847a85979f8d988c87.html"
    },
    {
      "date": "",
      "time": "11:00 UTC -5",
      "category": "SOCCER",
      "info": "World Cup Qualifier",
      "title": "Sao Tome and Principe - Tunisia",
      "url": "https://voodc.com/embed/85818c919d889b84847a85979f8e988c88.html"
    },
    {
      "date": "",
      "time": "11:00 UTC -5",
      "category": "SOCCER",
      "info": "World Cup Qualifier",
      "title": "Zimbabwe - South Africa",
      "url": "https://voodc.com/embed/85818c919d889b84847a85979f8f988c89.html"
    },
    {
      "date": "",
      "time": "11:00 UTC -5",
      "category": "HOCKEY",
      "info": "CZ Extraliga",
      "title": "HC Olomouc - HC Kometa Brno",
      "url": "https://voodc.com/embed/85818c919d889b84847a85979f90988a88.html"
    },
    {
      "date": "",
      "time": "11:00 UTC -5",
      "category": "HOCKEY",
      "info": "Polish Hockey League",
      "title": "Krakow - Torun",
      "url": "https://voodc.com/embed/85818c919d889b84847a8597a087988a89.html"
    },
    {
      "date": "",
      "time": "11:00 UTC -5",
      "category": "HOCKEY",
      "info": "Slovak Extraliga",
      "title": "Dukla Trencin - Michalovce",
      "url": "https://voodc.com/embed/85818c919d889b84847a8597a088988a8a.html"
    },
    {
      "date": "",
      "time": "11:00 UTC -5",
      "category": "HOCKEY",
      "info": "Slovak Extraliga",
      "title": "Poprad - Zvolen",
      "url": "https://voodc.com/embed/85818c919d889b84847a8597a089988a8b.html"
    },
    {
      "date": "",
      "time": "11:00 UTC -5",
      "category": "HOCKEY",
      "info": "Slovak Extraliga",
      "title": "Presov - HK Nitra",
      "url": "https://voodc.com/embed/85818c919d889b84847a8597a08a988a8c.html"
    },
    {
      "date": "",
      "time": "11:00 UTC -5",
      "category": "BASKETBALL",
      "info": "Poland Basket Liga",
      "title": "Ostrow Wielkopolski - Dabrowa Gornicza",
      "url": "https://voodc.com/embed/85818c919d889b84847a8597a08b98898d.html"
    },
    {
      "date": "",
      "time": "11:00 UTC -5",
      "category": "BASKETBALL",
      "info": "Turkey Basketball Super Lig",
      "title": "Besiktas - Buyukcekmece",
      "url": "https://voodc.com/embed/85818c919d889b84847a8597a08c988a84.html"
    },
    {
      "date": "",
      "time": "11:00 UTC -5",
      "category": "HANDBALL",
      "info": "Poland Superliga Women",
      "title": "Piotrcovia W - Start Elblag W",
      "url": "https://voodc.com/embed/85818c919d889b84847a8597a08d988a87.html"
    },
    {
      "date": "",
      "time": "11:00 UTC -5",
      "category": "BEACH VOLLEYBALL",
      "info": "BPT",
      "title": "Beach Pro Tour Elite 16: Newport Beach - Court 1",
      "url": "https://voodc.com/embed/85818c919d889b84847a859aa38f988a85.html"
    },
    {
      "date": "",
      "time": "11:00 UTC -5",
      "category": "BEACH VOLLEYBALL",
      "info": "BPT",
      "title": "Beach Pro Tour Elite 16: Newport Beach - Court 2",
      "url": "https://voodc.com/embed/85818c919d889b84847a859aa390988a86.html"
    },
    {
      "date": "",
      "time": "11:00 UTC -5",
      "category": "FIELD HOCKEY",
      "info": "Euro League Hockey",
      "title": "Campo - Leopold",
      "url": "https://voodc.com/embed/85818c919d889b84847a859a9d8e988d8a.html"
    },
    {
      "date": "",
      "time": "11:15 UTC -5",
      "category": "SOCCER",
      "info": "Euro Qualifier",
      "title": "Italy U21 - Sweden U21",
      "url": "https://voodc.com/embed/85818c919d889b8d847a8597a08e988c8a.html"
    },
    {
      "date": "",
      "time": "11:30 UTC -5",
      "category": "SOCCER",
      "info": "Bundesliga Women",
      "title": "RB Leipzig W - SGS Essen W",
      "url": "https://voodc.com/embed/85818c919d889c8c847a8597a08f988d88.html"
    },
    {
      "date": "",
      "time": "11:30 UTC -5",
      "category": "SOCCER",
      "info": "Euro Qualifier",
      "title": "Switzerland U21 - Iceland U21",
      "url": "https://voodc.com/embed/85818c919d889c8c847a8597a090988d89.html"
    },
    {
      "date": "",
      "time": "11:30 UTC -5",
      "category": "HOCKEY",
      "info": "CZ Extraliga",
      "title": "Sparta Prague - Dynamo Pardubice",
      "url": "https://voodc.com/embed/85818c919d889c8c847a8597a187988c8b.html"
    },
    {
      "date": "",
      "time": "11:30 UTC -5",
      "category": "HOCKEY",
      "info": "ICEHL",
      "title": "Graz99ers - Ferencvaros",
      "url": "https://voodc.com/embed/85818c919d889c8c847a8597a188988c8c.html"
    },
    {
      "date": "",
      "time": "11:30 UTC -5",
      "category": "HOCKEY",
      "info": "KHL",
      "title": "Dynamo Moscow - CSKA Moscow",
      "url": "https://voodc.com/embed/85818c919d889c8c847a8597a189988c8d.html"
    },
    {
      "date": "",
      "time": "11:30 UTC -5",
      "category": "HOCKEY",
      "info": "KHL",
      "title": "Spartak Moscow - Salavat Ufa",
      "url": "https://voodc.com/embed/85818c919d889c8c847a8597a18a988d84.html"
    },
    {
      "date": "",
      "time": "11:30 UTC -5",
      "category": "HOCKEY",
      "info": "Liiga",
      "title": "Assat - Tappara Tampere",
      "url": "https://voodc.com/embed/85818c919d889c8c847a8597a18b988d85.html"
    },
    {
      "date": "",
      "time": "11:30 UTC -5",
      "category": "HOCKEY",
      "info": "Polish Hockey League",
      "title": "Katowice - Bytom",
      "url": "https://voodc.com/embed/85818c919d889c8c847a8597a18c988d86.html"
    },
    {
      "date": "",
      "time": "11:30 UTC -5",
      "category": "HOCKEY",
      "info": "Slovak Extraliga",
      "title": "Slovan Bratislava - Liptovsky Mikulas",
      "url": "https://voodc.com/embed/85818c919d889c8c847a8597a18d988d87.html"
    },
    {
      "date": "",
      "time": "11:40 UTC -5",
      "category": "MOTORSPORT",
      "info": "IMSA",
      "title": "IMSA Pilot Challenge Race: FOX Factory 120",
      "url": "https://voodc.com/embed/85818c919d889d88847a859aa58e988d8b.html"
    },
    {
      "date": "",
      "time": "12:00 UTC -5",
      "category": "SOCCER",
      "info": "Euro Qualifier",
      "title": "Turkey U21 - Lithuania U21",
      "url": "https://voodc.com/embed/85818c919d889e8a847a8597a18e9885857b.html"
    },
    {
      "date": "",
      "time": "12:00 UTC -5",
      "category": "SOCCER",
      "info": "Euro Qualifier",
      "title": "Wales U21 - Belgium U21",
      "url": "https://voodc.com/embed/85818c919d889e8a847a8597a18f9885857c.html"
    },
    {
      "date": "",
      "time": "12:00 UTC -5",
      "category": "SOCCER",
      "info": "Friendly",
      "title": "Russia - Iran",
      "url": "https://voodc.com/embed/85818c919d889e8a847a8597a1909885857d.html"
    },
    {
      "date": "",
      "time": "12:00 UTC -5",
      "category": "SOCCER",
      "info": "Sweden Div 1",
      "title": "Ariana - Angelholm",
      "url": "https://voodc.com/embed/85818c919d889e8a847a8597a2879885857e.html"
    },
    {
      "date": "",
      "time": "12:00 UTC -5",
      "category": "SOCCER",
      "info": "Sweden Div 1",
      "title": "Husqvarna - IFK Skovde",
      "url": "https://voodc.com/embed/85818c919d889e8a847a859aa58d9885857f.html"
    },
    {
      "date": "",
      "time": "12:00 UTC -5",
      "category": "HOCKEY",
      "info": "HockeyAllsvenskan",
      "title": "AIK - Mora",
      "url": "https://voodc.com/embed/85818c919d889e8a847a8597a2889885847c.html"
    },
    {
      "date": "",
      "time": "12:00 UTC -5",
      "category": "HOCKEY",
      "info": "HockeyAllsvenskan",
      "title": "Almtuna - Oskarshamn",
      "url": "https://voodc.com/embed/85818c919d889e8a847a8597a2899885847d.html"
    },
    {
      "date": "",
      "time": "12:00 UTC -5",
      "category": "HOCKEY",
      "info": "HockeyAllsvenskan",
      "title": "Kalmar - IF Bjorkloven",
      "url": "https://voodc.com/embed/85818c919d889e8a847a8597a28a9885847e.html"
    },
    {
      "date": "",
      "time": "12:00 UTC -5",
      "category": "HOCKEY",
      "info": "HockeyAllsvenskan",
      "title": "Modo - Sodertalje",
      "url": "https://voodc.com/embed/85818c919d889e8a847a8597a28b9885847f.html"
    },
    {
      "date": "",
      "time": "12:00 UTC -5",
      "category": "HOCKEY",
      "info": "HockeyAllsvenskan",
      "title": "Ostersund - BIK Karlskoga",
      "url": "https://voodc.com/embed/85818c919d889e8a847a8597a28c98858480.html"
    },
    {
      "date": "",
      "time": "12:00 UTC -5",
      "category": "HOCKEY",
      "info": "HockeyAllsvenskan",
      "title": "Troja/Ljungby - Vasteras",
      "url": "https://voodc.com/embed/85818c919d889e8a847a8597a28d98858481.html"
    },
    {
      "date": "",
      "time": "12:00 UTC -5",
      "category": "HOCKEY",
      "info": "HockeyAllsvenskan",
      "title": "Vimmerby - Nybro",
      "url": "https://voodc.com/embed/85818c919d889e8a847a8597a28e98858482.html"
    },
    {
      "date": "",
      "time": "12:00 UTC -5",
      "category": "HOCKEY",
      "info": "Metal Ligaen",
      "title": "Esbjerg - Rungsted",
      "url": "https://voodc.com/embed/85818c919d889e8a847a8597a28f98858483.html"
    },
    {
      "date": "",
      "time": "12:00 UTC -5",
      "category": "HOCKEY",
      "info": "Polish Hockey League",
      "title": "Zaglebie Sosnowiec - Unia Oswiecim",
      "url": "https://voodc.com/embed/85818c919d889e8a847a8597a2909885857a.html"
    },
    {
      "date": "",
      "time": "12:00 UTC -5",
      "category": "BASKETBALL",
      "info": "Poland 1. Liga",
      "title": "Leszno - Miners Katowice",
      "url": "https://voodc.com/embed/85818c919d889e8a847a8597a387988d8c.html"
    },
    {
      "date": "",
      "time": "12:00 UTC -5",
      "category": "BASKETBALL",
      "info": "Poland 1. Liga",
      "title": "Spojnia Stargard - Poli. Opolska",
      "url": "https://voodc.com/embed/85818c919d889e8a847a8597a388988d8d.html"
    },
    {
      "date": "",
      "time": "12:00 UTC -5",
      "category": "HANDBALL",
      "info": "2. Bundesliga",
      "title": "Essen - Grosswallstadt",
      "url": "https://voodc.com/embed/85818c919d889e8a847a8597a3899885847a.html"
    },
    {
      "date": "",
      "time": "12:00 UTC -5",
      "category": "HANDBALL",
      "info": "Bundesliga",
      "title": "MT Melsungen - Leipzig",
      "url": "https://voodc.com/embed/85818c919d889e8a847a8597a38a9885847b.html"
    },
    {
      "date": "",
      "time": "12:04 UTC -5",
      "category": "BASKETBALL",
      "info": "Sweden Basketligan",
      "title": "Boras - Sodertalje",
      "url": "https://voodc.com/embed/85818c919d889e8c887a8597a38b98858580.html"
    },
    {
      "date": "",
      "time": "12:04 UTC -5",
      "category": "BASKETBALL",
      "info": "Sweden Basketligan",
      "title": "Nassjo - Hogsbo",
      "url": "https://voodc.com/embed/85818c919d889e8c887a8597a38c98858581.html"
    },
    {
      "date": "",
      "time": "12:04 UTC -5",
      "category": "BASKETBALL",
      "info": "Sweden Basketligan",
      "title": "Norrkoping - Uppsala",
      "url": "https://voodc.com/embed/85818c919d889e8c887a8597a38d98858582.html"
    },
    {
      "date": "",
      "time": "12:04 UTC -5",
      "category": "BASKETBALL",
      "info": "Sweden Basketligan",
      "title": "Umea - Koping Stars",
      "url": "https://voodc.com/embed/85818c919d889e8c887a8597a38e98858583.html"
    },
    {
      "date": "",
      "time": "12:15 UTC -5",
      "category": "HOCKEY",
      "info": "ICEHL",
      "title": "FC Salzburg - Vienna Capitals",
      "url": "https://voodc.com/embed/85818c919d889f89847a8597a38f9885867a.html"
    },
    {
      "date": "",
      "time": "12:15 UTC -5",
      "category": "HOCKEY",
      "info": "ICEHL",
      "title": "HK Olimpija - Black Wings Linz",
      "url": "https://voodc.com/embed/85818c919d889f89847a8597a3909885867b.html"
    },
    {
      "date": "",
      "time": "12:30 UTC -5",
      "category": "SOCCER",
      "info": "Argentina Liga Profesional",
      "title": "San Lorenzo - San Martin de San Juan",
      "url": "https://voodc.com/embed/85818c919d88a088847a8597a4879885877b.html"
    },
    {
      "date": "",
      "time": "12:30 UTC -5",
      "category": "SOCCER",
      "info": "Sweden Div 1",
      "title": "Orebro Syr. - Enkopings SK",
      "url": "https://voodc.com/embed/85818c919d88a088847a8597a4889885877c.html"
    },
    {
      "date": "",
      "time": "12:30 UTC -5",
      "category": "HOCKEY",
      "info": "DEL",
      "title": "Augsburger Panther - Grizzly Wolfsburg",
      "url": "https://voodc.com/embed/85818c919d88a088847a8597a4899885867d.html"
    },
    {
      "date": "",
      "time": "12:30 UTC -5",
      "category": "HOCKEY",
      "info": "DEL",
      "title": "Fischtown Pinguins - Adler Mannheim",
      "url": "https://voodc.com/embed/85818c919d88a088847a8597a48a9885867e.html"
    },
    {
      "date": "",
      "time": "12:30 UTC -5",
      "category": "HOCKEY",
      "info": "DEL",
      "title": "Frankfurt Lowen - Eisbaren Berlin",
      "url": "https://voodc.com/embed/85818c919d88a088847a8597a48b9885867f.html"
    },
    {
      "date": "",
      "time": "12:30 UTC -5",
      "category": "HOCKEY",
      "info": "DEL",
      "title": "Iserlohn Roosters - Dresdner Eislowen",
      "url": "https://voodc.com/embed/85818c919d88a088847a8597a48c98858680.html"
    },
    {
      "date": "",
      "time": "12:30 UTC -5",
      "category": "HOCKEY",
      "info": "DEL",
      "title": "Kolner Haie - ERC Ingolstadt",
      "url": "https://voodc.com/embed/85818c919d88a088847a8597a48d98858681.html"
    },
    {
      "date": "",
      "time": "12:30 UTC -5",
      "category": "HOCKEY",
      "info": "DEL",
      "title": "Straubing Tigers - Schwenninger Wild Wings",
      "url": "https://voodc.com/embed/85818c919d88a088847a8597a48e98858682.html"
    },
    {
      "date": "",
      "time": "12:30 UTC -5",
      "category": "HOCKEY",
      "info": "Metal Ligaen",
      "title": "AaB Aalborg - Sonderjyske Ishockey",
      "url": "https://voodc.com/embed/85818c919d88a088847a8597a48f98858683.html"
    },
    {
      "date": "",
      "time": "12:30 UTC -5",
      "category": "HOCKEY",
      "info": "Metal Ligaen",
      "title": "Herlev - Rodovre Mighty Bulls",
      "url": "https://voodc.com/embed/85818c919d88a088847a8597a4909885877a.html"
    },
    {
      "date": "",
      "time": "12:30 UTC -5",
      "category": "HANDBALL",
      "info": "2. Bundesliga",
      "title": "Ferndorf - Bietigheim-Metterzimmern",
      "url": "https://voodc.com/embed/85818c919d88a088847a8597a5879885867c.html"
    },
    {
      "date": "",
      "time": "12:45 UTC -5",
      "category": "HOCKEY",
      "info": "ICEHL",
      "title": "Val Pusteria - Bolzano",
      "url": "https://voodc.com/embed/85818c919d88a187847a8597a5889885877f.html"
    },
    {
      "date": "",
      "time": "12:45 UTC -5",
      "category": "HOCKEY",
      "info": "Swiss National League",
      "title": "Ambri-Piotta - Ajoie",
      "url": "https://voodc.com/embed/85818c919d88a187847a8597a58998858780.html"
    },
    {
      "date": "",
      "time": "12:45 UTC -5",
      "category": "HOCKEY",
      "info": "Swiss National League",
      "title": "EV Zug - Geneve-Servette",
      "url": "https://voodc.com/embed/85818c919d88a187847a8597a58a98858781.html"
    },
    {
      "date": "",
      "time": "12:45 UTC -5",
      "category": "HOCKEY",
      "info": "Swiss National League",
      "title": "Lausanne - Biel",
      "url": "https://voodc.com/embed/85818c919d88a187847a8597a58b98858782.html"
    },
    {
      "date": "",
      "time": "12:45 UTC -5",
      "category": "HOCKEY",
      "info": "Swiss National League",
      "title": "Lugano - Langnau Tigers",
      "url": "https://voodc.com/embed/85818c919d88a187847a8597a58c98858783.html"
    },
    {
      "date": "",
      "time": "12:45 UTC -5",
      "category": "HOCKEY",
      "info": "Swiss National League",
      "title": "Rapperswil-Jona - FC Zurich",
      "url": "https://voodc.com/embed/85818c919d88a187847a85989c879885887a.html"
    },
    {
      "date": "",
      "time": "12:45 UTC -5",
      "category": "BASKETBALL",
      "info": "EuroLeague",
      "title": "Fenerbahce - Crvena zvezda [english]",
      "url": "https://voodc.com/embed/85818c919d88a187847a85989c889885877d.html"
    },
    {
      "date": "",
      "time": "12:45 UTC -5",
      "category": "BASKETBALL",
      "info": "EuroLeague",
      "title": "Fenerbahce - Crvena zvezda [serbian]",
      "url": "https://voodc.com/embed/85818c919d88a187847a85989c899885877e.html"
    },
    {
      "date": "",
      "time": "13:00 UTC -5",
      "category": "BASKETBALL",
      "info": "BBL",
      "title": "Chemnitz - Ludwigsburg",
      "url": "https://voodc.com/embed/85818c919d88a286847a85989c8a9885887b.html"
    },
    {
      "date": "",
      "time": "13:00 UTC -5",
      "category": "HANDBALL",
      "info": "2. Bundesliga",
      "title": "N-Lubbecke - Lubeck-Schwartau",
      "url": "https://voodc.com/embed/85818c919d88a286847a85989c8b9885887d.html"
    },
    {
      "date": "",
      "time": "13:00 UTC -5",
      "category": "HANDBALL",
      "info": "Denmark Kvindeligaen",
      "title": "Viborg W - Horsens W",
      "url": "https://voodc.com/embed/85818c919d88a286847a85989c8c9885887e.html"
    },
    {
      "date": "",
      "time": "13:00 UTC -5",
      "category": "HANDBALL",
      "info": "France Starligue",
      "title": "Chartres - Dunkerque",
      "url": "https://voodc.com/embed/85818c919d88a286847a85989c8d9885887f.html"
    },
    {
      "date": "",
      "time": "13:00 UTC -5",
      "category": "HANDBALL",
      "info": "France Starligue",
      "title": "Istres - Montpellier",
      "url": "https://voodc.com/embed/85818c919d88a286847a85989c8e98858880.html"
    },
    {
      "date": "",
      "time": "13:00 UTC -5",
      "category": "HANDBALL",
      "info": "France Starligue",
      "title": "Limoges - Tremblay",
      "url": "https://voodc.com/embed/85818c919d88a286847a85989c8f98858881.html"
    },
    {
      "date": "",
      "time": "13:00 UTC -5",
      "category": "DARTS",
      "info": "PDC",
      "title": "World Grand Prix Darts",
      "url": "https://voodc.com/embed/85818c919d88a286847a85989c909885887c.html"
    },
    {
      "date": "",
      "time": "13:15 UTC -5",
      "category": "SOCCER",
      "info": "Eerste Divisie",
      "title": "Almere City - Vitesse",
      "url": "https://voodc.com/embed/85818c919d899985847a85989d879885897b.html"
    },
    {
      "date": "",
      "time": "13:15 UTC -5",
      "category": "BASKETBALL",
      "info": "EuroLeague",
      "title": "Olympiacos - Dubai [english]",
      "url": "https://voodc.com/embed/85818c919d899985847a85989d8898858882.html"
    },
    {
      "date": "",
      "time": "13:15 UTC -5",
      "category": "BASKETBALL",
      "info": "EuroLeague",
      "title": "Olympiacos - Dubai [spanish]",
      "url": "https://voodc.com/embed/85818c919d899985847a85989d8998858883.html"
    },
    {
      "date": "",
      "time": "13:15 UTC -5",
      "category": "BASKETBALL",
      "info": "Poland Basket Liga",
      "title": "Anwil Wloclawek - Gdynia",
      "url": "https://voodc.com/embed/85818c919d899985847a85989d8a9885897a.html"
    },
    {
      "date": "",
      "time": "13:30 UTC -5",
      "category": "SOCCER",
      "info": "Argentina Primera B",
      "title": "Laferrere - Acassuso",
      "url": "https://voodc.com/embed/85818c919d899a84847a85989d8b98858982.html"
    },
    {
      "date": "",
      "time": "13:30 UTC -5",
      "category": "SOCCER",
      "info": "Euro Qualifier",
      "title": "Ireland U21 - Slovakia U21",
      "url": "https://voodc.com/embed/85818c919d899a84847a85989d8c98858983.html"
    },
    {
      "date": "",
      "time": "13:30 UTC -5",
      "category": "SOCCER",
      "info": "Euro Qualifier",
      "title": "Portugal U21 - Bulgaria U21",
      "url": "https://voodc.com/embed/85818c919d899a84847a85989d8d98858a7a.html"
    },
    {
      "date": "",
      "time": "13:30 UTC -5",
      "category": "SOCCER",
      "info": "Italy Serie C",
      "title": "Arezzo - Gubbio",
      "url": "https://voodc.com/embed/85818c919d899a84847a85989d8e98858a7b.html"
    },
    {
      "date": "",
      "time": "13:30 UTC -5",
      "category": "SOCCER",
      "info": "Italy Serie C",
      "title": "Bra - Carpi",
      "url": "https://voodc.com/embed/85818c919d899a84847a85989d8f98858a7c.html"
    },
    {
      "date": "",
      "time": "13:30 UTC -5",
      "category": "SOCCER",
      "info": "LaLiga2",
      "title": "Granada CF - Las Palmas",
      "url": "https://voodc.com/embed/85818c919d899a84847a85989d9098858a7d.html"
    },
    {
      "date": "",
      "time": "13:30 UTC -5",
      "category": "HOCKEY",
      "info": "UK Elite League",
      "title": "Glasgow - Manchester",
      "url": "https://voodc.com/embed/85818c919d899a84847a85989e8798858981.html"
    },
    {
      "date": "",
      "time": "13:30 UTC -5",
      "category": "BASKETBALL",
      "info": "EuroLeague",
      "title": "Barcelona - Valencia Basket [english]",
      "url": "https://voodc.com/embed/85818c919d899a84847a85989e889885897c.html"
    },
    {
      "date": "",
      "time": "13:30 UTC -5",
      "category": "BASKETBALL",
      "info": "EuroLeague",
      "title": "Barcelona - Valencia Basket [spanish]",
      "url": "https://voodc.com/embed/85818c919d899a84847a85989e899885897d.html"
    },
    {
      "date": "",
      "time": "13:30 UTC -5",
      "category": "BASKETBALL",
      "info": "EuroLeague",
      "title": "Bayern Munich - Zalgiris Kaunas [english]",
      "url": "https://voodc.com/embed/85818c919d899a84847a85989e8a9885897e.html"
    },
    {
      "date": "",
      "time": "13:30 UTC -5",
      "category": "BASKETBALL",
      "info": "EuroLeague",
      "title": "Bayern Munich - Zalgiris Kaunas [spanish]",
      "url": "https://voodc.com/embed/85818c919d899a84847a85989e8b9885897f.html"
    },
    {
      "date": "",
      "time": "13:30 UTC -5",
      "category": "HANDBALL",
      "info": "France Starligue",
      "title": "Dijon - Cesson Rennes-Metropole",
      "url": "https://voodc.com/embed/85818c919d899a84847a85989e8c98858980.html"
    },
    {
      "date": "",
      "time": "13:45 UTC -5",
      "category": "SOCCER",
      "info": "World Cup Qualifier",
      "title": "Belgium - North Macedonia [english]",
      "url": "https://voodc.com/embed/85818c919d899a8d847a85989e8d98858a81.html"
    },
    {
      "date": "",
      "time": "13:45 UTC -5",
      "category": "SOCCER",
      "info": "World Cup Qualifier",
      "title": "Belgium - North Macedonia [dutch]",
      "url": "https://voodc.com/embed/85818c919d899a8d847a85989e8e98858a82.html"
    },
    {
      "date": "",
      "time": "13:45 UTC -5",
      "category": "SOCCER",
      "info": "World Cup Qualifier",
      "title": "Belgium - North Macedonia [spanish]",
      "url": "https://voodc.com/embed/85818c919d899a8d847a85989e8f98858a83.html"
    },
    {
      "date": "",
      "time": "13:45 UTC -5",
      "category": "SOCCER",
      "info": "World Cup Qualifier",
      "title": "France - Azerbaijan [english]",
      "url": "https://voodc.com/embed/85818c919d899a8d847a85989e9098858b7a.html"
    },
    {
      "date": "",
      "time": "13:45 UTC -5",
      "category": "SOCCER",
      "info": "World Cup Qualifier",
      "title": "France - Azerbaijan [spanish]",
      "url": "https://voodc.com/embed/85818c919d899a8d847a85989f8798858b7b.html"
    },
    {
      "date": "",
      "time": "13:45 UTC -5",
      "category": "SOCCER",
      "info": "World Cup Qualifier",
      "title": "Germany - Luxembourg [english]",
      "url": "https://voodc.com/embed/85818c919d899a8d847a85989f8898858b7c.html"
    },
    {
      "date": "",
      "time": "13:45 UTC -5",
      "category": "SOCCER",
      "info": "World Cup Qualifier",
      "title": "Germany - Luxembourg [german]",
      "url": "https://voodc.com/embed/85818c919d899a8d847a85989f8998858b7d.html"
    },
    {
      "date": "",
      "time": "13:45 UTC -5",
      "category": "SOCCER",
      "info": "World Cup Qualifier",
      "title": "Germany - Luxembourg [spanish]",
      "url": "https://voodc.com/embed/85818c919d899a8d847a85989f8a98858b7e.html"
    },
    {
      "date": "",
      "time": "13:45 UTC -5",
      "category": "SOCCER",
      "info": "World Cup Qualifier",
      "title": "Iceland - Ukraine [english]",
      "url": "https://voodc.com/embed/85818c919d899a8d847a85989f8b98858b7f.html"
    },
    {
      "date": "",
      "time": "13:45 UTC -5",
      "category": "SOCCER",
      "info": "World Cup Qualifier",
      "title": "Iceland - Ukraine [icelandic]",
      "url": "https://voodc.com/embed/85818c919d899a8d847a85989f8c98858b80.html"
    },
    {
      "date": "",
      "time": "13:45 UTC -5",
      "category": "SOCCER",
      "info": "World Cup Qualifier",
      "title": "Iceland - Ukraine [spanish]",
      "url": "https://voodc.com/embed/85818c919d899a8d847a85989f8d98858b81.html"
    },
    {
      "date": "",
      "time": "13:45 UTC -5",
      "category": "SOCCER",
      "info": "World Cup Qualifier",
      "title": "Kosovo - Slovenia [english]",
      "url": "https://voodc.com/embed/85818c919d899a8d847a85989f8e98858b82.html"
    },
    {
      "date": "",
      "time": "13:45 UTC -5",
      "category": "SOCCER",
      "info": "World Cup Qualifier",
      "title": "Kosovo - Slovenia [spanish]",
      "url": "https://voodc.com/embed/85818c919d899a8d847a85989f8f98858b83.html"
    },
    {
      "date": "",
      "time": "13:45 UTC -5",
      "category": "SOCCER",
      "info": "World Cup Qualifier",
      "title": "Northern Ireland - Slovakia [english]",
      "url": "https://voodc.com/embed/85818c919d899a8d847a85989f9098858c7a.html"
    },
    {
      "date": "",
      "time": "13:45 UTC -5",
      "category": "SOCCER",
      "info": "World Cup Qualifier",
      "title": "Northern Ireland - Slovakia [slovak]",
      "url": "https://voodc.com/embed/85818c919d899a8d847a8598a08798858c7b.html"
    },
    {
      "date": "",
      "time": "13:45 UTC -5",
      "category": "SOCCER",
      "info": "World Cup Qualifier",
      "title": "Northern Ireland - Slovakia [spanish]",
      "url": "https://voodc.com/embed/85818c919d899a8d847a8598a08898858c7c.html"
    },
    {
      "date": "",
      "time": "13:45 UTC -5",
      "category": "SOCCER",
      "info": "World Cup Qualifier",
      "title": "Sweden - Switzerland [english]",
      "url": "https://voodc.com/embed/85818c919d899a8d847a8598a08998858c7d.html"
    },
    {
      "date": "",
      "time": "13:45 UTC -5",
      "category": "SOCCER",
      "info": "World Cup Qualifier",
      "title": "Sweden - Switzerland [german]",
      "url": "https://voodc.com/embed/85818c919d899a8d847a8598a08a98858c7e.html"
    },
    {
      "date": "",
      "time": "13:45 UTC -5",
      "category": "SOCCER",
      "info": "World Cup Qualifier",
      "title": "Sweden - Switzerland [spanish]",
      "url": "https://voodc.com/embed/85818c919d899a8d847a8598a08b98858c7f.html"
    },
    {
      "date": "",
      "time": "13:45 UTC -5",
      "category": "RUGBY",
      "info": "Premiership Rugby",
      "title": "Sale Sharks - Newcastle Red Bulls",
      "url": "https://voodc.com/embed/85818c919d899a8d847a8598a08c98858a7e.html"
    },
    {
      "date": "",
      "time": "13:45 UTC -5",
      "category": "RUGBY",
      "info": "URC",
      "title": "Munster - Edinburgh",
      "url": "https://voodc.com/embed/85818c919d899a8d847a8598a08d98858a7f.html"
    },
    {
      "date": "",
      "time": "13:45 UTC -5",
      "category": "RUGBY",
      "info": "URC",
      "title": "Scarlets - Stormers",
      "url": "https://voodc.com/embed/85818c919d899a8d847a8598a08e98858a80.html"
    },
    {
      "date": "",
      "time": "14:00 UTC -5",
      "category": "SOCCER",
      "info": "Friendly",
      "title": "Spain U21 - Norway U21",
      "url": "https://voodc.com/embed/85818c919d899b8c847a8598a08f98858c83.html"
    },
    {
      "date": "",
      "time": "14:00 UTC -5",
      "category": "SOCCER",
      "info": "Ireland",
      "title": "Shamrock Rovers - Shelbourne",
      "url": "https://voodc.com/embed/85818c919d899b8c847a8598a09098858d7a.html"
    },
    {
      "date": "",
      "time": "14:00 UTC -5",
      "category": "SOCCER",
      "info": "Uruguay Segunda Div",
      "title": "Fenix - Tacuarembo",
      "url": "https://voodc.com/embed/85818c919d899b8c847a8598a18798858d7b.html"
    },
    {
      "date": "",
      "time": "14:00 UTC -5",
      "category": "HANDBALL",
      "info": "Portugal",
      "title": "Porto - Avanca",
      "url": "https://voodc.com/embed/85818c919d899b8c847a8598a18898858c82.html"
    },
    {
      "date": "",
      "time": "14:00 UTC -5",
      "category": "GOLF",
      "info": "Korn Ferry",
      "title": "Korn Ferry Tour Championship",
      "url": "https://voodc.com/embed/85818c919d899b8c847a8597a58d98858c80.html"
    },
    {
      "date": "",
      "time": "14:00 UTC -5",
      "category": "GOLF",
      "info": "PGA Tour Champions",
      "title": "SAS Championship",
      "url": "https://voodc.com/embed/85818c919d899b8c847a8598a18998858c81.html"
    },
    {
      "date": "",
      "time": "14:15 UTC -5",
      "category": "SOCCER",
      "info": "Argentina Liga Profesional",
      "title": "Defensa y Justicia - Argentinos Jrs",
      "url": "https://voodc.com/embed/85818c919d899c8b847a8598a18a98858d7d.html"
    },
    {
      "date": "",
      "time": "14:15 UTC -5",
      "category": "MOTORSPORT",
      "info": "IMSA",
      "title": "IMSA Weathertech: Road Atlanta Qualifying",
      "url": "https://voodc.com/embed/85818c919d899c8b847a8598a18b98858d7c.html"
    },
    {
      "date": "",
      "time": "14:45 UTC -5",
      "category": "SOCCER",
      "info": "Argentina Liga Profesional",
      "title": "Central Cordoba - Union de Santa Fe",
      "url": "https://voodc.com/embed/85818c919d899e89847a8598a18c98858d7e.html"
    },
    {
      "date": "",
      "time": "15:00 UTC -5",
      "category": "SOCCER",
      "info": "Colombia Primera B",
      "title": "Real Santander - Cucuta",
      "url": "https://voodc.com/embed/85818c919d899f88847a8598a18d98858d80.html"
    },
    {
      "date": "",
      "time": "15:00 UTC -5",
      "category": "CYCLING",
      "info": "UCI",
      "title": "UCI Mountain Bike World Series Women: Mont-Sainte-Anne",
      "url": "https://voodc.com/embed/85818c919d899f88847a8598a18e98858d7f.html"
    },
    {
      "date": "",
      "time": "15:30 UTC -5",
      "category": "SOCCER",
      "info": "Paraguay",
      "title": "Recoleta - Olimpia Asuncion",
      "url": "https://voodc.com/embed/85818c919d89a186847a8598a18f98858d81.html"
    },
    {
      "date": "",
      "time": "16:00 UTC -5",
      "category": "SOCCER",
      "info": "World Cup Qualifier",
      "title": "Suriname - Guatemala [spanish]",
      "url": "https://voodc.com/embed/85818c919d8a9984847a8598a1909886847a.html"
    },
    {
      "date": "",
      "time": "16:00 UTC -5",
      "category": "SOCCER",
      "info": "World Cup Qualifier",
      "title": "Suriname - Guatemala [english]",
      "url": "https://voodc.com/embed/85818c919d8a9984847a8598a2879886847b.html"
    },
    {
      "date": "",
      "time": "16:00 UTC -5",
      "category": "HOCKEY",
      "info": "NCAA",
      "title": "Quinnipiac Bobcats - Alaska Nanooks",
      "url": "https://voodc.com/embed/85818c919d8a9984847a8598a28898858d83.html"
    },
    {
      "date": "",
      "time": "16:00 UTC -5",
      "category": "CYCLING",
      "info": "UCI",
      "title": "UCI Mountain Bike World Series Men: Mont-Sainte-Anne",
      "url": "https://voodc.com/embed/85818c919d8a9984847a8598a18e98858d82.html"
    },
    {
      "date": "",
      "time": "16:30 UTC -5",
      "category": "SOCCER",
      "info": "Argentina Liga Profesional",
      "title": "Newell's Old Boys - CA Tigre",
      "url": "https://voodc.com/embed/85818c919d8a9a8c847a8598a2899886847c.html"
    },
    {
      "date": "",
      "time": "17:00 UTC -5",
      "category": "SOCCER",
      "info": "Liga AUF Uruguaya",
      "title": "Plaza Colonia - Progreso",
      "url": "https://voodc.com/embed/85818c919d8a9c8a847a8598a28a9886847e.html"
    },
    {
      "date": "",
      "time": "17:00 UTC -5",
      "category": "SOCCER",
      "info": "USL Super League",
      "title": "Lexington W - Carolina Ascent W",
      "url": "https://voodc.com/embed/85818c919d8a9c8a847a8598a28b9886847f.html"
    },
    {
      "date": "",
      "time": "17:00 UTC -5",
      "category": "SOCCER",
      "info": "World Cup Qualifier",
      "title": "Bermuda - Trinidad & Tobago",
      "url": "https://voodc.com/embed/85818c919d8a9c8a847a8598a28c98868480.html"
    },
    {
      "date": "",
      "time": "17:00 UTC -5",
      "category": "HOCKEY",
      "info": "NCAA",
      "title": "Niagara Purple Eagles - Bowling Green Falcons",
      "url": "https://voodc.com/embed/85818c919d8a9c8a847a8598a28d9886847d.html"
    },
    {
      "date": "",
      "time": "17:00 UTC -5",
      "category": "WATER SPORTS",
      "info": "Swimming",
      "title": "World Aquatics Swimming World Cup: Carmel",
      "url": "https://voodc.com/embed/85818c919d8a9c8a847a8598a28e98868481.html"
    },
    {
      "date": "",
      "time": "17:10 UTC -5",
      "category": "BASKETBALL",
      "info": "South American League",
      "title": "Ferro - Motilones del Norte",
      "url": "https://voodc.com/embed/85818c919d8a9d86847a8598a28f98868482.html"
    },
    {
      "date": "",
      "time": "17:30 UTC -5",
      "category": "SOCCER",
      "info": "USL1",
      "title": "One Knoxville - Portland Hearts of Pine",
      "url": "https://voodc.com/embed/85818c919d8a9e88847a8598a29098868483.html"
    },
    {
      "date": "",
      "time": "18:00 UTC -5",
      "category": "BOXING",
      "info": "Event",
      "title": "BKFC Ice Wars 3: Bare Knuckle Brawls",
      "url": "https://voodc.com/embed/85818c919d8aa086847a85959c879886857a.html"
    },
    {
      "date": "",
      "time": "18:00 UTC -5",
      "category": "BASKETBALL",
      "info": "NBA",
      "title": "Boston Celtics vs. Toronto Raptors [away feed]",
      "url": "https://voodc.com/embed/85818c919d8aa086847a85959c889886867d.html"
    },
    {
      "date": "",
      "time": "18:00 UTC -5",
      "category": "BASKETBALL",
      "info": "NBA",
      "title": "Boston Celtics vs. Toronto Raptors [home feed]",
      "url": "https://voodc.com/embed/85818c919d8aa086847a85959c899886867e.html"
    },
    {
      "date": "",
      "time": "18:00 UTC -5",
      "category": "BASKETBALL",
      "info": "NBA",
      "title": "Orlando Magic vs. Philadelphia 76ers",
      "url": "https://voodc.com/embed/85818c919d8aa086847a85959c8a9886867f.html"
    },
    {
      "date": "",
      "time": "18:00 UTC -5",
      "category": "AMERICAN FOOTBALL",
      "info": "NCAA",
      "title": "Brown vs. Bryant",
      "url": "https://voodc.com/embed/85818c919d8aa086847a85959c8b98868680.html"
    },
    {
      "date": "",
      "time": "18:00 UTC -5",
      "category": "AMERICAN FOOTBALL",
      "info": "NCAA",
      "title": "Cornell vs. Harvard",
      "url": "https://voodc.com/embed/85818c919d8aa086847a85959c8c98868681.html"
    },
    {
      "date": "",
      "time": "18:00 UTC -5",
      "category": "AMERICAN FOOTBALL",
      "info": "NCAA",
      "title": "Marist vs. Pennsylvania",
      "url": "https://voodc.com/embed/85818c919d8aa086847a85959c8d98868682.html"
    },
    {
      "date": "",
      "time": "18:00 UTC -5",
      "category": "SOCCER",
      "info": "Friendly",
      "title": "Chile - Peru",
      "url": "https://voodc.com/embed/85818c919d8aa086847a85959c8e98868683.html"
    },
    {
      "date": "",
      "time": "18:00 UTC -5",
      "category": "SOCCER",
      "info": "Mexico",
      "title": "Club Leon W - Pachuca W",
      "url": "https://voodc.com/embed/85818c919d8aa086847a85959c8f9886877a.html"
    },
    {
      "date": "",
      "time": "18:00 UTC -5",
      "category": "SOCCER",
      "info": "Paraguay",
      "title": "Sportivo Trinidense - General Caballero JLM",
      "url": "https://voodc.com/embed/85818c919d8aa086847a85959c909886877b.html"
    },
    {
      "date": "",
      "time": "18:00 UTC -5",
      "category": "SOCCER",
      "info": "USL",
      "title": "North Carolina - Phoenix Rising FC",
      "url": "https://voodc.com/embed/85818c919d8aa086847a85959d879886877c.html"
    },
    {
      "date": "",
      "time": "18:00 UTC -5",
      "category": "SOCCER",
      "info": "USL1",
      "title": "Charlotte Independence - AV Alta",
      "url": "https://voodc.com/embed/85818c919d8aa086847a85959d889886877d.html"
    },
    {
      "date": "",
      "time": "18:00 UTC -5",
      "category": "SOCCER",
      "info": "World Cup Qualifier",
      "title": "Curacao - Jamaica [english]",
      "url": "https://voodc.com/embed/85818c919d8aa086847a85959d899886877e.html"
    },
    {
      "date": "",
      "time": "18:00 UTC -5",
      "category": "SOCCER",
      "info": "World Cup Qualifier",
      "title": "Curacao - Jamaica [spanish]",
      "url": "https://voodc.com/embed/85818c919d8aa086847a85959d8a9886877f.html"
    },
    {
      "date": "",
      "time": "18:00 UTC -5",
      "category": "HOCKEY",
      "info": "AHL",
      "title": "Utica Comets - Cleveland Monsters",
      "url": "https://voodc.com/embed/85818c919d8aa086847a85959d8b9886857b.html"
    },
    {
      "date": "",
      "time": "18:00 UTC -5",
      "category": "HOCKEY",
      "info": "NCAA",
      "title": "Boston University Terriers - Colgate Raiders",
      "url": "https://voodc.com/embed/85818c919d8aa086847a85959d8c9886857c.html"
    },
    {
      "date": "",
      "time": "18:00 UTC -5",
      "category": "HOCKEY",
      "info": "NCAA",
      "title": "Canisius Golden Griffins - Long Island Sharks",
      "url": "https://voodc.com/embed/85818c919d8aa086847a85959d8d9886857d.html"
    },
    {
      "date": "",
      "time": "18:00 UTC -5",
      "category": "HOCKEY",
      "info": "NCAA",
      "title": "Ferris State Bulldogs - Western Michigan Broncos",
      "url": "https://voodc.com/embed/85818c919d8aa086847a85959d8e9886857e.html"
    },
    {
      "date": "",
      "time": "18:00 UTC -5",
      "category": "HOCKEY",
      "info": "NCAA",
      "title": "Maine Black Bears - Holy Cross Crusaders",
      "url": "https://voodc.com/embed/85818c919d8aa086847a85959d8f9886857f.html"
    },
    {
      "date": "",
      "time": "18:00 UTC -5",
      "category": "HOCKEY",
      "info": "NCAA",
      "title": "Mercyhurst Lakers - Union Dutchmen",
      "url": "https://voodc.com/embed/85818c919d8aa086847a85959d9098868580.html"
    },
    {
      "date": "",
      "time": "18:00 UTC -5",
      "category": "HOCKEY",
      "info": "NCAA",
      "title": "Merrimack Warriors - Massachusetts Lowell",
      "url": "https://voodc.com/embed/85818c919d8aa086847a85959e8798868581.html"
    },
    {
      "date": "",
      "time": "18:00 UTC -5",
      "category": "HOCKEY",
      "info": "NCAA",
      "title": "Northeastern Huskies - Army Black Knights",
      "url": "https://voodc.com/embed/85818c919d8aa086847a85959e8898868582.html"
    },
    {
      "date": "",
      "time": "18:00 UTC -5",
      "category": "HOCKEY",
      "info": "NCAA",
      "title": "Providence Friars - Michigan Wolverines",
      "url": "https://voodc.com/embed/85818c919d8aa086847a85959e8998868583.html"
    },
    {
      "date": "",
      "time": "18:00 UTC -5",
      "category": "HOCKEY",
      "info": "NCAA",
      "title": "Rensselaer Engineers - Miami",
      "url": "https://voodc.com/embed/85818c919d8aa086847a85959e8a9886867a.html"
    },
    {
      "date": "",
      "time": "18:00 UTC -5",
      "category": "HOCKEY",
      "info": "NCAA",
      "title": "Stonehill - Massachusetts Minutemen",
      "url": "https://voodc.com/embed/85818c919d8aa086847a85959e8b9886867b.html"
    },
    {
      "date": "",
      "time": "18:00 UTC -5",
      "category": "HOCKEY",
      "info": "NCAA",
      "title": "Vermont Catamounts - St. Lawrence Saints",
      "url": "https://voodc.com/embed/85818c919d8aa086847a85959e8c9886867c.html"
    },
    {
      "date": "",
      "time": "18:00 UTC -5",
      "category": "VOLLEYBALL",
      "info": "NCAA",
      "title": "Ole Miss vs. Mississippi State",
      "url": "https://voodc.com/embed/85818c919d8aa086847a85959e8d98868780.html"
    },
    {
      "date": "",
      "time": "18:00 UTC -5",
      "category": "VOLLEYBALL",
      "info": "NCAA",
      "title": "Wisconsin W - Penn State W",
      "url": "https://voodc.com/embed/85818c919d8aa086847a85959e8e98868781.html"
    },
    {
      "date": "",
      "time": "18:05 UTC -5",
      "category": "HOCKEY",
      "info": "AHL",
      "title": "Rochester Americans - Toronto Marlies",
      "url": "https://voodc.com/embed/85818c919d8aa089847a85959e8f98868782.html"
    },
    {
      "date": "",
      "time": "18:05 UTC -5",
      "category": "HOCKEY",
      "info": "NCAA",
      "title": "RIT Tigers - Sacred Heart Pioneers",
      "url": "https://voodc.com/embed/85818c919d8aa089847a85959e9098868783.html"
    },
    {
      "date": "",
      "time": "18:07 UTC -5",
      "category": "HOCKEY",
      "info": "NCAA",
      "title": "Lake Superior State Lakers - Lindenwood Lions",
      "url": "https://voodc.com/embed/85818c919d8aa08a867a85959f879886887a.html"
    },
    {
      "date": "",
      "time": "18:30 UTC -5",
      "category": "AMERICAN FOOTBALL",
      "info": "NCAA",
      "title": "#24 South Florida vs. North Texas",
      "url": "https://voodc.com/embed/85818c919d8aa284847a85959f889886887b.html"
    },
    {
      "date": "",
      "time": "18:30 UTC -5",
      "category": "SOCCER",
      "info": "Colombia Primera B",
      "title": "Barranquilla - Cartagena",
      "url": "https://voodc.com/embed/85818c919d8aa284847a85959f899886887c.html"
    },
    {
      "date": "",
      "time": "18:30 UTC -5",
      "category": "SOCCER",
      "info": "Friendly",
      "title": "Canada - Australia",
      "url": "https://voodc.com/embed/85818c919d8aa284847a85959f8a9886887d.html"
    },
    {
      "date": "",
      "time": "18:30 UTC -5",
      "category": "SOCCER",
      "info": "NWSL",
      "title": "Racing Louisville W - Chicago Red Stars W",
      "url": "https://voodc.com/embed/85818c919d8aa284847a85959f8b9886887e.html"
    },
    {
      "date": "",
      "time": "19:00 UTC -5",
      "category": "COMBAT SPORT",
      "info": "WWE",
      "title": "WWE Friday Night SmackDown",
      "url": "https://voodc.com/embed/85818c919d8b998c847a85959f8c98868983.html"
    },
    {
      "date": "",
      "time": "19:00 UTC -5",
      "category": "BASKETBALL",
      "info": "NBA",
      "title": "Utah Jazz vs. San Antonio Spurs [away feed]",
      "url": "https://voodc.com/embed/85818c919d8b998c847a85959f8d98868883.html"
    },
    {
      "date": "",
      "time": "19:00 UTC -5",
      "category": "BASKETBALL",
      "info": "NBA",
      "title": "Utah Jazz vs. San Antonio Spurs [home feed]",
      "url": "https://voodc.com/embed/85818c919d8b998c847a85959f8e9886897a.html"
    },
    {
      "date": "",
      "time": "19:00 UTC -5",
      "category": "BASKETBALL",
      "info": "WNBA",
      "title": "Las Vegas Aces W vs. Phoenix Mercury W [english]",
      "url": "https://voodc.com/embed/85818c919d8b998c847a85959f8f98868981.html"
    },
    {
      "date": "",
      "time": "19:00 UTC -5",
      "category": "BASKETBALL",
      "info": "WNBA",
      "title": "Las Vegas Aces W vs. Phoenix Mercury W [spanish]",
      "url": "https://voodc.com/embed/85818c919d8b998c847a85959f9098868982.html"
    },
    {
      "date": "",
      "time": "19:00 UTC -5",
      "category": "SOCCER",
      "info": "Friendly",
      "title": "Argentina - Venezuela [spanish]",
      "url": "https://voodc.com/embed/85818c919d8b998c847a8595a0879886897b.html"
    },
    {
      "date": "",
      "time": "19:00 UTC -5",
      "category": "SOCCER",
      "info": "Friendly",
      "title": "Argentina - Venezuela [spanish alt]",
      "url": "https://voodc.com/embed/85818c919d8b998c847a8595a0889886897c.html"
    },
    {
      "date": "",
      "time": "19:00 UTC -5",
      "category": "SOCCER",
      "info": "Friendly",
      "title": "Argentina - Venezuela [spanish alt]",
      "url": "https://voodc.com/embed/85818c919d8b998c847a8595a0899886897d.html"
    },
    {
      "date": "",
      "time": "19:00 UTC -5",
      "category": "SOCCER",
      "info": "Friendly",
      "title": "Argentina - Venezuela [english]",
      "url": "https://voodc.com/embed/85818c919d8b998c847a8595a08a9886897e.html"
    },
    {
      "date": "",
      "time": "19:00 UTC -5",
      "category": "SOCCER",
      "info": "Friendly",
      "title": "Argentina - Venezuela [portuguese]",
      "url": "https://voodc.com/embed/85818c919d8b998c847a8595a08b9886897f.html"
    },
    {
      "date": "",
      "time": "19:00 UTC -5",
      "category": "SOCCER",
      "info": "NWSL",
      "title": "Orlando Pride W - Portland Thorns W",
      "url": "https://voodc.com/embed/85818c919d8b998c847a8595a08c98868980.html"
    },
    {
      "date": "",
      "time": "19:00 UTC -5",
      "category": "HOCKEY",
      "info": "AHL",
      "title": "Manitoba Moose - Laval Rocket",
      "url": "https://voodc.com/embed/85818c919d8b998c847a8595a08d98868880.html"
    },
    {
      "date": "",
      "time": "19:00 UTC -5",
      "category": "HOCKEY",
      "info": "AHL",
      "title": "Texas Stars - Grand Rapids Griffins",
      "url": "https://voodc.com/embed/85818c919d8b998c847a8595a08e98868881.html"
    },
    {
      "date": "",
      "time": "19:00 UTC -5",
      "category": "HOCKEY",
      "info": "NCAA",
      "title": "Omaha Mavericks - Minnesota State Mavericks",
      "url": "https://voodc.com/embed/85818c919d8b998c847a8595a08f98868882.html"
    },
    {
      "date": "",
      "time": "19:00 UTC -5",
      "category": "BASKETBALL",
      "info": "Argentina Liga A",
      "title": "Gimnasia - Olimpico",
      "url": "https://voodc.com/embed/85818c919d8b998c847a8595a0909886887f.html"
    },
    {
      "date": "",
      "time": "19:07 UTC -5",
      "category": "HOCKEY",
      "info": "NCAA",
      "title": "Bemidji State Beavers - St. Cloud State Huskies",
      "url": "https://voodc.com/embed/85818c919d8b9a86867a8595a18798868a7a.html"
    },
    {
      "date": "",
      "time": "19:07 UTC -5",
      "category": "HOCKEY",
      "info": "NCAA",
      "title": "Minnesota Duluth Bulldogs - Augustana Vikings",
      "url": "https://voodc.com/embed/85818c919d8b9a86867a8595a18898868a7b.html"
    },
    {
      "date": "",
      "time": "19:07 UTC -5",
      "category": "HOCKEY",
      "info": "NCAA",
      "title": "North Dakota Fighting Hawks - St. Thomas Tommies",
      "url": "https://voodc.com/embed/85818c919d8b9a86867a8595a18998868a7c.html"
    },
    {
      "date": "",
      "time": "19:08 UTC -5",
      "category": "BASEBALL",
      "info": "MLB",
      "title": "Detroit Tigers vs. Seattle Mariners",
      "url": "https://voodc.com/embed/85818c919d8b9a868c7a8595a18a98868a7d.html"
    },
    {
      "date": "",
      "time": "19:08 UTC -5",
      "category": "BASEBALL",
      "info": "MLB",
      "title": "Detroit Tigers vs. Seattle Mariners [spanish]",
      "url": "https://voodc.com/embed/85818c919d8b9a868c7a8595a18b98868a7e.html"
    },
    {
      "date": "",
      "time": "19:30 UTC -5",
      "category": "COMBAT SPORT",
      "info": "MMA",
      "title": "Cage Fury 147",
      "url": "https://voodc.com/embed/85818c919d8b9b8a847a8595a18c98868a7f.html"
    },
    {
      "date": "",
      "time": "19:30 UTC -5",
      "category": "SOCCER",
      "info": "Friendly",
      "title": "USA - Ecuador [english]",
      "url": "https://voodc.com/embed/85818c919d8b9b8a847a8595a18d98868a80.html"
    },
    {
      "date": "",
      "time": "19:30 UTC -5",
      "category": "SOCCER",
      "info": "Friendly",
      "title": "USA - Ecuador [spanish]",
      "url": "https://voodc.com/embed/85818c919d8b9b8a847a8595a18e98868a81.html"
    },
    {
      "date": "",
      "time": "19:40 UTC -5",
      "category": "BASKETBALL",
      "info": "South American League",
      "title": "Univ. Sucre - Vasco",
      "url": "https://voodc.com/embed/85818c919d8b9c86847a8595a18f98868a82.html"
    },
    {
      "date": "",
      "time": "20:00 UTC -5",
      "category": "COMBAT SPORT",
      "info": "MMA",
      "title": "LFA 219",
      "url": "https://voodc.com/embed/85818c919d8b9d88847a8595a19098868b7e.html"
    },
    {
      "date": "",
      "time": "20:00 UTC -5",
      "category": "BOXING",
      "info": "Event",
      "title": "Deonte Brown vs. Grimardi Machuca",
      "url": "https://voodc.com/embed/85818c919d8b9d88847a8595a28798868a83.html"
    },
    {
      "date": "",
      "time": "20:00 UTC -5",
      "category": "AMERICAN FOOTBALL",
      "info": "CFL",
      "title": "Toronto Argonauts vs. Saskatchewan Roughriders",
      "url": "https://voodc.com/embed/85818c919d8b9d88847a8595a28898868b7a.html"
    },
    {
      "date": "",
      "time": "20:00 UTC -5",
      "category": "AMERICAN FOOTBALL",
      "info": "NCAA",
      "title": "Fresno State vs. Colorado State",
      "url": "https://voodc.com/embed/85818c919d8b9d88847a8595a28998868b7f.html"
    },
    {
      "date": "",
      "time": "20:00 UTC -5",
      "category": "AMERICAN FOOTBALL",
      "info": "NCAA",
      "title": "Rutgers vs. Washington",
      "url": "https://voodc.com/embed/85818c919d8b9d88847a8595a28a98868b80.html"
    },
    {
      "date": "",
      "time": "20:00 UTC -5",
      "category": "SOCCER",
      "info": "Mexico",
      "title": "Club America W - Tigres UANL W",
      "url": "https://voodc.com/embed/85818c919d8b9d88847a8595a28b98868b83.html"
    },
    {
      "date": "",
      "time": "20:00 UTC -5",
      "category": "SOCCER",
      "info": "Mexico Liga de Expansion",
      "title": "Alebrijes Oaxaca - Atletico La Paz",
      "url": "https://voodc.com/embed/85818c919d8b9d88847a8595a28c98868b81.html"
    },
    {
      "date": "",
      "time": "20:00 UTC -5",
      "category": "SOCCER",
      "info": "Mexico Liga de Expansion",
      "title": "Cancun - Irapuato",
      "url": "https://voodc.com/embed/85818c919d8b9d88847a8595a28d98868b82.html"
    },
    {
      "date": "",
      "time": "20:00 UTC -5",
      "category": "SOCCER",
      "info": "World Cup Qualifier",
      "title": "El Salvador - Panama [spanish]",
      "url": "https://voodc.com/embed/85818c919d8b9d88847a8595a28e98868c7a.html"
    },
    {
      "date": "",
      "time": "20:00 UTC -5",
      "category": "SOCCER",
      "info": "World Cup Qualifier",
      "title": "El Salvador - Panama [spanish alt]",
      "url": "https://voodc.com/embed/85818c919d8b9d88847a8595a28f98868c7b.html"
    },
    {
      "date": "",
      "time": "20:00 UTC -5",
      "category": "SOCCER",
      "info": "World Cup Qualifier",
      "title": "El Salvador - Panama [english]",
      "url": "https://voodc.com/embed/85818c919d8b9d88847a8595a29098868c7c.html"
    },
    {
      "date": "",
      "time": "20:00 UTC -5",
      "category": "HOCKEY",
      "info": "NCAA",
      "title": "Arizona State Sun Devils - Notre Dame Fighting Irish",
      "url": "https://voodc.com/embed/85818c919d8b9d88847a8595a38798868b7b.html"
    },
    {
      "date": "",
      "time": "20:00 UTC -5",
      "category": "HOCKEY",
      "info": "NCAA",
      "title": "Colorado College Tigers - Bentley Falcons",
      "url": "https://voodc.com/embed/85818c919d8b9d88847a8595a38898868b7c.html"
    },
    {
      "date": "",
      "time": "20:00 UTC -5",
      "category": "VOLLEYBALL",
      "info": "NCAA",
      "title": "Baylor W - Arizona W",
      "url": "https://voodc.com/embed/85818c919d8b9d88847a8595a38998868c7d.html"
    },
    {
      "date": "",
      "time": "20:00 UTC -5",
      "category": "VOLLEYBALL",
      "info": "NCAA",
      "title": "Washington W - Nebraska W",
      "url": "https://voodc.com/embed/85818c919d8b9d88847a8595a38a98868c7e.html"
    },
    {
      "date": "",
      "time": "20:00 UTC -5",
      "category": "MMA* COMBAT FC 11",
      "info": "",
      "title": "",
      "url": "https://voodc.com/embed/85818c919d8b9d88847a8595a38b98868b7d.html"
    },
    {
      "date": "",
      "time": "20:05 UTC -5",
      "category": "HOCKEY",
      "info": "AHL",
      "title": "Colorado Eagles - Calgary Wranglers",
      "url": "https://voodc.com/embed/85818c919d8b9d8b847a8595a38c98868c7f.html"
    },
    {
      "date": "",
      "time": "20:30 UTC -5",
      "category": "SOCCER",
      "info": "Canada",
      "title": "Cavalry - Forge",
      "url": "https://voodc.com/embed/85818c919d8b9f86847a8595a38d98868c80.html"
    },
    {
      "date": "",
      "time": "21:00 UTC -5",
      "category": "COMBAT SPORT",
      "info": "MMA",
      "title": "A1 Combat 31",
      "url": "https://voodc.com/embed/85818c919d8ba184847a8595a38e98868d7b.html"
    },
    {
      "date": "",
      "time": "21:00 UTC -5",
      "category": "BASKETBALL",
      "info": "NBA",
      "title": "Sacramento Kings vs. Portland Trail Blazers [away feed]",
      "url": "https://voodc.com/embed/85818c919d8ba184847a8595a38f98868d7c.html"
    },
    {
      "date": "",
      "time": "21:00 UTC -5",
      "category": "BASKETBALL",
      "info": "NBA",
      "title": "Sacramento Kings vs. Portland Trail Blazers [home feed]",
      "url": "https://voodc.com/embed/85818c919d8ba184847a8595a39098868d7d.html"
    },
    {
      "date": "",
      "time": "21:00 UTC -5",
      "category": "SOCCER",
      "info": "Mexico Liga de Expansion",
      "title": "Venados - Tepatitlan de Morelos",
      "url": "https://voodc.com/embed/85818c919d8ba184847a8595a48798868d7e.html"
    },
    {
      "date": "",
      "time": "21:00 UTC -5",
      "category": "HOCKEY",
      "info": "AHL",
      "title": "Coachella Valley Firebirds - San Diego Gulls",
      "url": "https://voodc.com/embed/85818c919d8ba184847a8595a48898868c82.html"
    },
    {
      "date": "",
      "time": "21:00 UTC -5",
      "category": "HOCKEY",
      "info": "AHL",
      "title": "Henderson Silver Knights - Abbotsford Canucks",
      "url": "https://voodc.com/embed/85818c919d8ba184847a8595a48998868c83.html"
    },
    {
      "date": "",
      "time": "21:00 UTC -5",
      "category": "HOCKEY",
      "info": "AHL",
      "title": "Ontario Reign - Tucson Roadrunners",
      "url": "https://voodc.com/embed/85818c919d8ba184847a8595a48a98868d7a.html"
    },
    {
      "date": "",
      "time": "21:00 UTC -5",
      "category": "BASKETBALL",
      "info": "New Zealand",
      "title": "Southern Hoiho W - Tokomanawa Queens W",
      "url": "https://voodc.com/embed/85818c919d8ba184847a8595a48b98868c81.html"
    },
    {
      "date": "",
      "time": "21:00 UTC -5",
      "category": "VOLLEYBALL",
      "info": "NCAA",
      "title": "Colorado W - Arizona State W",
      "url": "https://voodc.com/embed/85818c919d8ba184847a8595a48c98868d7f.html"
    },
    {
      "date": "",
      "time": "21:05 UTC -5",
      "category": "AUSSIE RULES",
      "info": "AFL",
      "title": "Adelaide Crows W - West Coast Eagles W",
      "url": "https://voodc.com/embed/85818c919d8ba187847a8595a48d98878482.html"
    },
    {
      "date": "",
      "time": "21:30 UTC -5",
      "category": "SOCCER",
      "info": "NWSL",
      "title": "Seattle Reign W - Bay FC W",
      "url": "https://voodc.com/embed/85818c919d8ba28c847a8595a48e98868d80.html"
    },
    {
      "date": "",
      "time": "22:00 UTC -5",
      "category": "SOCCER",
      "info": "Mexico",
      "title": "Club Tijuana W - Monterrey W",
      "url": "https://voodc.com/embed/85818c919d8c9a8a847a8595a48f98868d83.html"
    },
    {
      "date": "",
      "time": "22:00 UTC -5",
      "category": "GOLF",
      "info": "LPGA",
      "title": "LPGA Shanghai",
      "url": "https://voodc.com/embed/85818c919d8c9a8a847a8595a49098868d81.html"
    },
    {
      "date": "",
      "time": "22:00 UTC -5",
      "category": "GOLF",
      "info": "PGA Tour",
      "title": "Baycurrent Classic",
      "url": "https://voodc.com/embed/85818c919d8c9a8a847a8595a58798868d82.html"
    },
    {
      "date": "",
      "time": "22:10 UTC -5",
      "category": "RUGBY",
      "info": "New Zealand Bunnings NPC",
      "title": "Bay of Plenty - Tasman",
      "url": "https://voodc.com/embed/85818c919d8c9b86847a8595a5889887847a.html"
    },
    {
      "date": "",
      "time": "23:05 UTC -5",
      "category": "AUSSIE RULES",
      "info": "AFL",
      "title": "Geelong Cats W - GWS Giants W",
      "url": "https://voodc.com/embed/85818c919d8c9e89847a8595a58998878483.html"
    },
    {
      "date": "",
      "time": "23:05 UTC -5",
      "category": "AUSSIE RULES",
      "info": "AFL",
      "title": "Hawthorn Hawks W - Gold Coast Suns W",
      "url": "https://voodc.com/embed/85818c919d8c9e89847a8595a48d9887857a.html"
    },
    {
      "date": "",
      "time": "00:00 UTC -5",
      "category": "SOCCER",
      "info": "J3-League",
      "title": "Giravanz Kitakyushu - Kagoshima Utd",
      "url": "https://voodc.com/embed/85818c919d8ca18c847a8595a58a9887847b.html"
    },
    {
      "date": "",
      "time": "00:00 UTC -5",
      "category": "SOCCER",
      "info": "J3-League",
      "title": "Tochigi City - Nara Club",
      "url": "https://voodc.com/embed/85818c919d8ca18c847a8595a58b9887847c.html"
    },
    {
      "date": "",
      "time": "00:00 UTC -5",
      "category": "SOCCER",
      "info": "K League 2",
      "title": "Gimpo FC - Seoul E-Land",
      "url": "https://voodc.com/embed/85818c919d8ca18c847a8595a58c9887847d.html"
    },
    {
      "date": "",
      "time": "00:00 UTC -5",
      "category": "VOLLEYBALL",
      "info": "NCAA",
      "title": "Cal Poly W - Hawaii W",
      "url": "https://voodc.com/embed/85818c919d8ca18c847a8595a58d9887847e.html"
    },
    {
      "date": "",
      "time": "01:05 UTC -5",
      "category": "AUSSIE RULES",
      "info": "AFL",
      "title": "Brisbane Lions W - Port Adelaide W",
      "url": "https://voodc.com/embed/85818c919d8d9b8b847a8595a58e9887857b.html"
    },
    {
      "date": "",
      "time": "01:10 UTC -5",
      "category": "RUGBY",
      "info": "New Zealand Bunnings NPC",
      "title": "Hawke's Bay - Taranaki",
      "url": "https://voodc.com/embed/85818c919d8d9c84847a8595a58f9887847f.html"
    },
    {
      "date": "",
      "time": "02:30 UTC -5",
      "category": "SOCCER",
      "info": "K League 2",
      "title": "Hwaseong - Cheongju",
      "url": "https://voodc.com/embed/85818c919d8da08c847a8595a59098878480.html"
    },
    {
      "date": "",
      "time": "02:45 UTC -5",
      "category": "FIELD HOCKEY",
      "info": "Euro Hockey League",
      "title": "Western Wildcats - Braxgata",
      "url": "https://voodc.com/embed/85818c919d8da18b847a85969c8798878481.html"
    },
    {
      "date": "",
      "time": "03:15 UTC -5",
      "category": "AUSSIE RULES",
      "info": "AFL",
      "title": "Richmond W - North Melbourne W",
      "url": "https://voodc.com/embed/85818c919d8e9989847a8595a58e9887857c.html"
    }
  ]
}
