
{
  "events": [
    
    {
      "date": "",
      "time": "06:00 UTC -5",
      "category": "BILLIARD",
      "info": "Snooker",
      "title": "Championship League Snooker - Table 1",
      "url": "https://voodc.com/embed/85818c98a48e9984847a85979c8798858d.html"
    },
    {
      "date": "",
      "time": "06:00 UTC -5",
      "category": "BILLIARD",
      "info": "Snooker",
      "title": "Championship League Snooker - Table 2",
      "url": "https://voodc.com/embed/85818c98a48e9984847a85979c88988684.html"
    },
    {
      "date": "",
      "time": "11:30 UTC -5",
      "category": "HOCKEY",
      "info": "Mestis",
      "title": "Jokerit - Hermes",
      "url": "https://voodc.com/embed/85818c98a48fa28c847a859a9e8a988887.html"
    },
    {
      "date": "",
      "time": "12:30 UTC -5",
      "category": "BASKETBALL",
      "info": "NCAA",
      "title": "Hofstra vs. Towson",
      "url": "https://voodc.com/embed/85818c98a4909c88847a859a9e8c98888d.html"
    },
    {
      "date": "",
      "time": "12:30 UTC -5",
      "category": "SOCCER",
      "info": "Saudi Professional League",
      "title": "Al Nassr - Al Qadsiah [english]",
      "url": "https://voodc.com/embed/85818c98a4909c88847a859a9e8d988984.html"
    },
    {
      "date": "",
      "time": "12:30 UTC -5",
      "category": "SOCCER",
      "info": "Saudi Professional League",
      "title": "Al Nassr - Al Qadsiah [spanish]",
      "url": "https://voodc.com/embed/85818c98a4909c88847a859a9e8e988985.html"
    },
    {
      "date": "",
      "time": "12:30 UTC -5",
      "category": "SOCCER",
      "info": "Serie A",
      "title": "Cremonese - Cagliari [english]",
      "url": "https://voodc.com/embed/85818c98a4909c88847a859a9e8f988986.html"
    },
    {
      "date": "",
      "time": "12:30 UTC -5",
      "category": "SOCCER",
      "info": "Serie A",
      "title": "Cremonese - Cagliari [spanish]",
      "url": "https://voodc.com/embed/85818c98a4909c88847a859a9e90988987.html"
    },
    {
      "date": "",
      "time": "12:30 UTC -5",
      "category": "HOCKEY",
      "info": "Norway EHL",
      "title": "Frisk Asker - Lorenskog",
      "url": "https://voodc.com/embed/85818c98a4909c88847a859a9f8798888a.html"
    },
    {
      "date": "",
      "time": "12:30 UTC -5",
      "category": "HOCKEY",
      "info": "Norway EHL",
      "title": "Nidaros - Lillehammer",
      "url": "https://voodc.com/embed/85818c98a4909c88847a859a9f8898888b.html"
    },
    {
      "date": "",
      "time": "12:30 UTC -5",
      "category": "HOCKEY",
      "info": "Norway EHL",
      "title": "Stavanger Oilers - Narvik",
      "url": "https://voodc.com/embed/85818c98a4909c88847a859a9f8998888c.html"
    },
    {
      "date": "",
      "time": "13:00 UTC -5",
      "category": "SOCCER",
      "info": "France Super Cup",
      "title": "PSG - Marseille [english]",
      "url": "https://voodc.com/embed/85818c98a4909e86847a85979c8b988a86.html"
    },
    {
      "date": "",
      "time": "13:00 UTC -5",
      "category": "SOCCER",
      "info": "France Super Cup",
      "title": "PSG - Marseille [spanish]",
      "url": "https://voodc.com/embed/85818c98a4909e86847a85979c8c988a87.html"
    },
    {
      "date": "",
      "time": "13:00 UTC -5",
      "category": "HOCKEY",
      "info": "Norway EHL",
      "title": "Valerenga - Sparta Sarpsborg",
      "url": "https://voodc.com/embed/85818c98a4909e86847a85979c8d988988.html"
    },
    {
      "date": "",
      "time": "13:00 UTC -5",
      "category": "HOCKEY",
      "info": "SHL",
      "title": "Djurgarden - Orebro",
      "url": "https://voodc.com/embed/85818c98a4909e86847a85979c8e988989.html"
    },
    {
      "date": "",
      "time": "13:00 UTC -5",
      "category": "HOCKEY",
      "info": "SHL",
      "title": "Frolunda Gothenburg - Lulea Hockey",
      "url": "https://voodc.com/embed/85818c98a4909e86847a85979c8f98898a.html"
    },
    {
      "date": "",
      "time": "13:00 UTC -5",
      "category": "HOCKEY",
      "info": "SHL",
      "title": "Leksand - Linkoping",
      "url": "https://voodc.com/embed/85818c98a4909e86847a85979c9098898b.html"
    },
    {
      "date": "",
      "time": "13:00 UTC -5",
      "category": "HOCKEY",
      "info": "SHL",
      "title": "Malmo - Brynas",
      "url": "https://voodc.com/embed/85818c98a4909e86847a85979d8798898c.html"
    },
    {
      "date": "",
      "time": "13:00 UTC -5",
      "category": "HOCKEY",
      "info": "SHL",
      "title": "Skelleftea AIK - HV71 Jonkoping",
      "url": "https://voodc.com/embed/85818c98a4909e86847a85979d8898898d.html"
    },
    {
      "date": "",
      "time": "13:00 UTC -5",
      "category": "HOCKEY",
      "info": "SHL",
      "title": "Timra - Rogle",
      "url": "https://voodc.com/embed/85818c98a4909e86847a85979d89988a84.html"
    },
    {
      "date": "",
      "time": "13:00 UTC -5",
      "category": "HOCKEY",
      "info": "SHL",
      "title": "Vaxjo Lakers - Farjestad",
      "url": "https://voodc.com/embed/85818c98a4909e86847a85979d8a988a85.html"
    },
    {
      "date": "",
      "time": "13:00 UTC -5",
      "category": "VOLLEYBALL",
      "info": "CEV Challenge Cup",
      "title": "CAV Esquimo W - Panionios W",
      "url": "https://voodc.com/embed/85818c98a4909e86847a85979d8b988a88.html"
    },
    {
      "date": "",
      "time": "13:04 UTC -5",
      "category": "BASKETBALL",
      "info": "Sweden Basketligan",
      "title": "Boras - Sloga Uppsala",
      "url": "https://voodc.com/embed/85818c98a4909e88887a85979d8c988a89.html"
    },
    {
      "date": "",
      "time": "13:15 UTC -5",
      "category": "SOCCER",
      "info": "Brazil Copinha",
      "title": "Meia Noite U20 - Coritiba U20",
      "url": "https://voodc.com/embed/85818c98a4909f85847a85979d8d988a8a.html"
    },
    {
      "date": "",
      "time": "13:30 UTC -5",
      "category": "HOCKEY",
      "info": "DEL",
      "title": "Iserlohn Roosters - Eisbaren Berlin",
      "url": "https://voodc.com/embed/85818c98a490a084847a85979d8e988a8d.html"
    },
    {
      "date": "",
      "time": "13:30 UTC -5",
      "category": "BASKETBALL",
      "info": "Champions League",
      "title": "Promitheas - Chalon/Saone",
      "url": "https://voodc.com/embed/85818c98a490a084847a85979d8f988a8b.html"
    },
    {
      "date": "",
      "time": "13:30 UTC -5",
      "category": "HANDBALL",
      "info": "Friendly",
      "title": "Spain - Slovakia",
      "url": "https://voodc.com/embed/85818c98a490a084847a85979d90988a8c.html"
    },
    {
      "date": "",
      "time": "13:45 UTC -5",
      "category": "HOCKEY",
      "info": "Swiss National League",
      "title": "Fribourg-Gotteron - EV Zug",
      "url": "https://voodc.com/embed/85818c98a490a08d847a85979e87988b84.html"
    },
    {
      "date": "",
      "time": "13:45 UTC -5",
      "category": "HOCKEY",
      "info": "Swiss National League",
      "title": "Geneve-Servette - Lugano",
      "url": "https://voodc.com/embed/85818c98a490a08d847a85979e88988b85.html"
    },
    {
      "date": "",
      "time": "14:00 UTC -5",
      "category": "SOCCER",
      "info": "Spain Super Cup",
      "title": "Atletico Madrid - Real Madrid [english]",
      "url": "https://voodc.com/embed/85818c98a490a18c847a85979e89988b8b.html"
    },
    {
      "date": "",
      "time": "14:00 UTC -5",
      "category": "SOCCER",
      "info": "Spain Super Cup",
      "title": "Atletico Madrid - Real Madrid [spanish]",
      "url": "https://voodc.com/embed/85818c98a490a18c847a85979e8a988b8c.html"
    },
    {
      "date": "",
      "time": "14:00 UTC -5",
      "category": "SOCCER",
      "info": "Spain Super Cup",
      "title": "Atletico Madrid - Real Madrid [portuguese]",
      "url": "https://voodc.com/embed/85818c98a490a18c847a85979e8b988b8d.html"
    },
    {
      "date": "",
      "time": "14:00 UTC -5",
      "category": "SOCCER",
      "info": "Spain Super Cup",
      "title": "Atletico Madrid - Real Madrid [serbian]",
      "url": "https://voodc.com/embed/85818c98a490a18c847a85979e8c988c84.html"
    },
    {
      "date": "",
      "time": "14:00 UTC -5",
      "category": "HOCKEY",
      "info": "Swiss National League",
      "title": "Rapperswil-Jona - Langnau Tigers",
      "url": "https://voodc.com/embed/85818c98a490a18c847a85979e8d988b8a.html"
    },
    {
      "date": "",
      "time": "14:00 UTC -5",
      "category": "BASKETBALL",
      "info": "BBL",
      "title": "Jena - Rostock",
      "url": "https://voodc.com/embed/85818c98a490a18c847a85979e8e988b86.html"
    },
    {
      "date": "",
      "time": "14:00 UTC -5",
      "category": "BASKETBALL",
      "info": "Champions League",
      "title": "Le Mans - Mersin SK",
      "url": "https://voodc.com/embed/85818c98a490a18c847a85979e8f988b87.html"
    },
    {
      "date": "",
      "time": "14:00 UTC -5",
      "category": "BASKETBALL",
      "info": "Champions League",
      "title": "Trieste - Szolnoki Olaj",
      "url": "https://voodc.com/embed/85818c98a490a18c847a85979e90988b88.html"
    },
    {
      "date": "",
      "time": "14:00 UTC -5",
      "category": "VOLLEYBALL",
      "info": "CEV Champions League",
      "title": "ACH Ljubljana - Ziraat Bankasi",
      "url": "https://voodc.com/embed/85818c98a490a18c847a85979f87988c85.html"
    },
    {
      "date": "",
      "time": "14:00 UTC -5",
      "category": "VOLLEYBALL",
      "info": "CEV Champions League",
      "title": "Le Cannet W - Alba Blaj W",
      "url": "https://voodc.com/embed/85818c98a490a18c847a85979f88988c86.html"
    },
    {
      "date": "",
      "time": "14:00 UTC -5",
      "category": "VOLLEYBALL",
      "info": "CEV Champions League",
      "title": "Scandicci W - Vakifbank W",
      "url": "https://voodc.com/embed/85818c98a490a18c847a85979f89988c87.html"
    },
    {
      "date": "",
      "time": "14:00 UTC -5",
      "category": "VOLLEYBALL",
      "info": "Poland I. Liga",
      "title": "Mickiewicz Kluczbork - Stal Nysa",
      "url": "https://voodc.com/embed/85818c98a490a18c847a85979f8a988c88.html"
    },
    {
      "date": "",
      "time": "14:00 UTC -5",
      "category": "FLOORBALL",
      "info": "European Championship",
      "title": "Germany - Ireland",
      "url": "https://voodc.com/embed/85818c98a490a18c847a85979f8b988b89.html"
    },
    {
      "date": "",
      "time": "14:15 UTC -5",
      "category": "BASKETBALL",
      "info": "EuroLeague",
      "title": "Panathinaikos - Virtus Bologna [english]",
      "url": "https://voodc.com/embed/85818c98a490a28b847a85979f8c988c89.html"
    },
    {
      "date": "",
      "time": "14:15 UTC -5",
      "category": "BASKETBALL",
      "info": "EuroLeague",
      "title": "Panathinaikos - Virtus Bologna [spanish]",
      "url": "https://voodc.com/embed/85818c98a490a28b847a85979f8d988c8a.html"
    },
    {
      "date": "",
      "time": "14:15 UTC -5",
      "category": "BASKETBALL",
      "info": "Iceland",
      "title": "Akranes IA - Grindavik",
      "url": "https://voodc.com/embed/85818c98a490a28b847a85979f8e988c8b.html"
    },
    {
      "date": "",
      "time": "14:15 UTC -5",
      "category": "BASKETBALL",
      "info": "Iceland",
      "title": "IR Reykjavik - Njardvik",
      "url": "https://voodc.com/embed/85818c98a490a28b847a85979f8f988c8c.html"
    },
    {
      "date": "",
      "time": "14:15 UTC -5",
      "category": "BASKETBALL",
      "info": "Iceland",
      "title": "KR Basket - Armann",
      "url": "https://voodc.com/embed/85818c98a490a28b847a85979f90988c8d.html"
    },
    {
      "date": "",
      "time": "14:15 UTC -5",
      "category": "BASKETBALL",
      "info": "Iceland",
      "title": "Valur - Stjarnan",
      "url": "https://voodc.com/embed/85818c98a490a28b847a8597a087988d84.html"
    },
    {
      "date": "",
      "time": "14:15 UTC -5",
      "category": "BASKETBALL",
      "info": "Poland Basket Liga",
      "title": "GTK Gliwice - Czarni Slupsk",
      "url": "https://voodc.com/embed/85818c98a490a28b847a8597a088988d85.html"
    },
    {
      "date": "",
      "time": "14:30 UTC -5",
      "category": "SOCCER",
      "info": "Brazil Copinha",
      "title": "Brasiliense U20 - Fluminense U20",
      "url": "https://voodc.com/embed/85818c98a587998a847a8597a089988d8c.html"
    },
    {
      "date": "",
      "time": "14:30 UTC -5",
      "category": "BASKETBALL",
      "info": "EuroLeague",
      "title": "Valencia Basket - Monaco [english]",
      "url": "https://voodc.com/embed/85818c98a587998a847a8597a08a988d86.html"
    },
    {
      "date": "",
      "time": "14:30 UTC -5",
      "category": "BASKETBALL",
      "info": "EuroLeague",
      "title": "Valencia Basket - Monaco [spanish]",
      "url": "https://voodc.com/embed/85818c98a587998a847a8597a08b988d87.html"
    },
    {
      "date": "",
      "time": "14:30 UTC -5",
      "category": "VOLLEYBALL",
      "info": "CEV Champions League",
      "title": "Roeselare - Lublin",
      "url": "https://voodc.com/embed/85818c98a587998a847a8597a08c988d8d.html"
    },
    {
      "date": "",
      "time": "14:45 UTC -5",
      "category": "SOCCER",
      "info": "Serie A",
      "title": "AC Milan - Genoa [english]",
      "url": "https://voodc.com/embed/85818c98a5879a89847a8597a08d9885847e.html"
    },
    {
      "date": "",
      "time": "14:45 UTC -5",
      "category": "SOCCER",
      "info": "Serie A",
      "title": "AC Milan - Genoa [spanish]",
      "url": "https://voodc.com/embed/85818c98a5879a89847a8597a08e9885847f.html"
    },
    {
      "date": "",
      "time": "14:45 UTC -5",
      "category": "BASKETBALL",
      "info": "EuroLeague",
      "title": "Real Madrid - Maccabi Tel Aviv [english]",
      "url": "https://voodc.com/embed/85818c98a5879a89847a8597a08f9885847a.html"
    },
    {
      "date": "",
      "time": "14:45 UTC -5",
      "category": "BASKETBALL",
      "info": "EuroLeague",
      "title": "Real Madrid - Maccabi Tel Aviv [hebrew]",
      "url": "https://voodc.com/embed/85818c98a5879a89847a8597a0909885847b.html"
    },
    {
      "date": "",
      "time": "14:45 UTC -5",
      "category": "BASKETBALL",
      "info": "EuroLeague",
      "title": "Real Madrid - Maccabi Tel Aviv [spanish]",
      "url": "https://voodc.com/embed/85818c98a5879a89847a8597a1879885847c.html"
    },
    {
      "date": "",
      "time": "14:45 UTC -5",
      "category": "HANDBALL",
      "info": "Friendly",
      "title": "Netherlands - Greece",
      "url": "https://voodc.com/embed/85818c98a5879a89847a8597a1889885847d.html"
    },
    {
      "date": "",
      "time": "15:00 UTC -5",
      "category": "BASKETBALL",
      "info": "NCAAW",
      "title": "Miami (W) - #10 Louisville (W)",
      "url": "https://voodc.com/embed/85818c98a5879b88847a8597a18998858480.html"
    },
    {
      "date": "",
      "time": "15:00 UTC -5",
      "category": "SOCCER",
      "info": "EPL",
      "title": "Arsenal - Liverpool [english]",
      "url": "https://voodc.com/embed/85818c98a5879b88847a8597a18a98858482.html"
    },
    {
      "date": "",
      "time": "15:00 UTC -5",
      "category": "SOCCER",
      "info": "EPL",
      "title": "Arsenal - Liverpool [spanish]",
      "url": "https://voodc.com/embed/85818c98a5879b88847a8597a18b98858483.html"
    },
    {
      "date": "",
      "time": "15:00 UTC -5",
      "category": "SOCCER",
      "info": "EPL",
      "title": "Arsenal - Liverpool [spanish alt]",
      "url": "https://voodc.com/embed/85818c98a5879b88847a8597a18c9885857a.html"
    },
    {
      "date": "",
      "time": "15:00 UTC -5",
      "category": "RUGBY",
      "info": "Pro D2",
      "title": "Provence Rugby - Grenoble FC",
      "url": "https://voodc.com/embed/85818c98a5879b88847a8597a18d98858481.html"
    },
    {
      "date": "",
      "time": "15:00 UTC -5",
      "category": "VOLLEYBALL",
      "info": "CEV Champions League",
      "title": "Benfica W - Novara W",
      "url": "https://voodc.com/embed/85818c98a5879b88847a8597a18e9885857b.html"
    },
    {
      "date": "",
      "time": "15:15 UTC -5",
      "category": "SOCCER",
      "info": "Liga Portugal 2",
      "title": "Lusitania FC - Leixoes",
      "url": "https://voodc.com/embed/85818c98a5879c87847a8597a18f9885857c.html"
    },
    {
      "date": "",
      "time": "15:30 UTC -5",
      "category": "BASKETBALL",
      "info": "NCAAW",
      "title": "East Texas A&M (W) - Texas A&M-Corpus Christi (W)",
      "url": "https://voodc.com/embed/85818c98a5879d86847a8597a1909885857d.html"
    }
  ]
}
